Workbook
Name Slicer_Age_Bracket: #N/A
Name Slicer_Region: #N/A

Sheet Customer
A1: CustomerID | B1: Name | C1: Gender | D1: Age | E1: Age Bracket | F1: Region | G1: Occupation | H1: Income | I1: Income Segment | J1: Customer_Segment | K1: Join_Date | L1: Year | M1: Customer Duration
A2: CUST0001 | B2: Mrs. Deborah Dominguez MD | C2: Male | D2: 38 | E2: Millennials | F2: North | G2: Doctor | H2: 191672 | I2: High | J2: Retail | K2: 45041 | L2: 2023 | M2: 1203 days
A3: CUST0002 | B3: Erin Martinez | C3: Female | D3: 49 | E3: Gen X | F3: East | G3: Trader | H3: 186472 | I3: High | J3: Corporate | K3: 44331 | L3: 2021 | M3: 1913 days
A4: CUST0003 | B4: Amanda Harris | C4: Male | D4: 40 | E4: Millennials | F4: North | G4: Teacher | H4: 155566 | I4: High | J4: Private | K4: 43438 | L4: 2018 | M4: 2806 days
A5: CUST0004 | B5: Candice Palmer | C5: Male | D5: 50 | E5: Gen X | F5: North | G5: Banker | H5: 142744 | I5: High | J5: Retail | K5: 44494 | L5: 2021 | M5: 1750 days
A6: CUST0005 | B6: Sandra Davis | C6: Male | D6: 20 | E6: Gen z | F6: West | G6: Student | H6: 109431 | I6: Medium | J6: Corporate | K6: 43309 | L6: 2018 | M6: 2935 days | S6: Checking | T6: Savings | U6: Loan | V6: Credit Card
A7: CUST0006 | B7: Vanessa Peterson | C7: Female | D7: 35 | E7: Millennials | F7: South | G7: Teacher | H7: 63001 | I7: Low | J7: Retail | K7: 42520 | L7: 2016 | M7: 3724 days | R7: Most Common account type | S7: =COUNTIF(Linked[Account Type],"Checking") -> 246 | T7: =COUNTIF(Linked[Account Type],"Savings") -> 303 | U7: =COUNTIF(Linked[Account Type],"Loan") -> 82 | V7: =COUNTIF(Linked[Account Type],"CreditCard") -> 169
A8: CUST0007 | B8: Tyler Fischer | C8: Male | D8: 42 | E8: Millennials | F8: North | G8: Engineer | H8: 87364 | I8: Medium | J8: Corporate | K8: 43026 | L8: 2017 | M8: 3218 days | R8: Count of Customers with multiple accounts
A9: CUST0008 | B9: William Horton | C9: Male | D9: 59 | E9: Gen X | F9: North | G9: Engineer | H9: 144988 | I9: High | J9: Retail | K9: 45448 | L9: 2024 | M9: 796 days | R9: Total amount of Approved Loans | S9: =SUMIF(Linked[Loan Status],"Approved",Linked[Loan Amount]) -> 3677399
A10: CUST0009 | B10: Donna Williams | C10: Male | D10: 48 | E10: Gen X | F10: West | G10: Retired | H10: 65028 | I10: Low | J10: Corporate | K10: 43507 | L10: 2019 | M10: 2737 days | S10: Retail | T10: Private | U10: Corporate
A11: CUST0010 | B11: Mary Casey | C11: Female | D11: 71 | E11: Boomers | F11: West | G11: Trader | H11: 188645 | I11: High | J11: Corporate | K11: 42405 | L11: 2016 | M11: 3839 days | R11: Highest Average Balance | S11: =AVERAGEIF(Linked[Customer Segment],"Retail",Linked[Balance]) -> 267102.03 | T11: =AVERAGEIF(Linked[Customer Segment],"Private",Linked[Balance]) -> 275113.66 | U11: =AVERAGEIF(Linked[Customer Segment],"Corporate",Linked[Balance]) -> 259460.32
A12: CUST0011 | B12: Kevin Phillips | C12: Male | D12: 20 | E12: Gen z | F12: South | G12: Doctor | H12: 151878 | I12: High | J12: Private | K12: 42781 | L12: 2017 | M12: 3463 days | R12: Average Balance | S12: =AVERAGE(Linked[Balance]) -> 265426.42
A13: CUST0012 | B13: Michael Richard | C13: Male | D13: 57 | E13: Gen X | F13: West | G13: Trader | H13: 144343 | I13: High | J13: Corporate | K13: 45280 | L13: 2023 | M13: 964 days | R13: Total Loan Amount | S13: =SUM(Linked[Loan Amount]) -> 43730664
A14: CUST0013 | B14: Jaime Davis MD | C14: Male | D14: 63 | E14: Boomers | F14: East | G14: Trader | H14: 148301 | I14: High | J14: Retail | K14: 45018 | L14: 2023 | M14: 1226 days | R14: Total Deposit Balance | S14: =SUMIF(Linked[Account Type],"Checking",Linked[Balance])+SUMIF(Linked[Account Type],"Savings",Linked[Balance]) -> 145013181
A15: CUST0014 | B15: Eric Peterson | C15: Male | D15: 41 | E15: Millennials | F15: West | G15: Trader | H15: 146295 | I15: High | J15: Corporate | K15: 42960 | L15: 2017 | M15: 3284 days | R15: Average Credit Score | S15: =AVERAGE(Linked[Credit Score]) -> 579.52625 | T15: =IF(S15<=579,"Poor",IF(S15<=669,"Fair",IF(S15<=739,"Good",IF(S15<=799,"Very Good",IF(S15>=800,"Excellent"))))) -> Fair
A16: CUST0015 | B16: Ms. Renee Cardenas PhD | C16: Female | D16: 67 | E16: Boomers | F16: East | G16: Trader | H16: 180829 | I16: High | J16: Corporate | K16: 43673 | L16: 2019 | M16: 2571 days | R16: No of Approved Loans
A17: CUST0016 | B17: Ashlee Baird | C17: Male | D17: 49 | E17: Gen X | F17: South | G17: Banker | H17: 54636 | I17: Low | J17: Retail | K17: 43643 | L17: 2019 | M17: 2601 days | R17: Checking Average credit score | S17: =AVERAGEIF(Linked[Account Type],"Checking",Linked[Credit Score]) -> 578.67073 | T17: =IF(S17<=579,"Poor",IF(S17<=669,"Fair",IF(S17<=739,"Good",IF(S17<=799,"Very Good",IF(S17>=800,"Excellent"))))) -> Poor
A18: CUST0017 | B18: Michael Conner | C18: Female | D18: 64 | E18: Boomers | F18: South | G18: Banker | H18: 199352 | I18: High | J18: Retail | K18: 44375 | L18: 2021 | M18: 1869 days | R18: Savings Average credit score | S18: =AVERAGEIF(Linked[Account Type],"Savings",Linked[Credit Score]) -> 586.9868 | T18: =IF(S18<=579,"Poor",IF(S18<=669,"Fair",IF(S18<=739,"Good",IF(S18<=799,"Very Good",IF(S18>=800,"Excellent"))))) -> Fair
A19: CUST0018 | B19: Jeff Koch | C19: Female | D19: 39 | E19: Millennials | F19: South | G19: Retired | H19: 44262 | I19: Low | J19: Private | K19: 45728 | L19: 2025 | M19: 516 days | R19: Loan Average credit score | S19: =AVERAGEIF(Linked[Account Type],"Loan",Linked[Credit Score]) -> 564 | T19: =IF(S19<=579,"Poor",IF(S19<=669,"Fair",IF(S19<=739,"Good",IF(S19<=799,"Very Good",IF(S19>=800,"Excellent"))))) -> Poor
A20: CUST0019 | B20: Melissa Clark | C20: Female | D20: 40 | E20: Millennials | F20: South | G20: Teacher | H20: 100435 | I20: Medium | J20: Corporate | K20: 44456 | L20: 2021 | M20: 1788 days | R20: CrediT Card Average credit score | S20: =AVERAGEIF(Linked[Account Type],"CreditCard",Linked[Credit Score]) -> 574.92899 | T20: =IF(S20<=579,"Poor",IF(S20<=669,"Fair",IF(S20<=739,"Good",IF(S20<=799,"Very Good",IF(S20>=800,"Excellent"))))) -> Poor
A21: CUST0020 | B21: Janice Scott | C21: Male | D21: 19 | E21: Gen z | F21: South | G21: Engineer | H21: 148583 | I21: High | J21: Corporate | K21: 45058 | L21: 2023 | M21: 1186 days | R21: AVG credit score of approved loans | S21: =GETPIVOTDATA("Credit Score",'Pivot Table'!$H$22,"Loan Status","Approved") -> 580.50877
A22: CUST0021 | B22: Elizabeth Smith | C22: Female | D22: 44 | E22: Millennials | F22: East | G22: Trader | H22: 189269 | I22: High | J22: Retail | K22: 45414 | L22: 2024 | M22: 830 days | R22: AVG credit score of Rejected loans | S22: =GETPIVOTDATA("Credit Score",'Pivot Table'!$H$22,"Loan Status","Rejected") -> 591.81159
A23: CUST0022 | B23: Jodi Burns | C23: Male | D23: 59 | E23: Gen X | F23: East | G23: Retired | H23: 61844 | I23: Low | J23: Corporate | K23: 45118 | L23: 2023 | M23: 1126 days | R23: Total Value of approved loans | S23: =SUMIF(Linked[Loan Status],"Approved",Linked[Loan Amount]) -> 3677399
A24: CUST0023 | B24: Robert Robertson | C24: Female | D24: 19 | E24: Gen z | F24: South | G24: Teacher | H24: 84754 | I24: Medium | J24: Retail | K24: 44745 | L24: 2022 | M24: 1499 days | R24: Total Balance | S24: =SUM(Linked[Balance]) -> 212341134
A25: CUST0024 | B25: Curtis Scott | C25: Female | D25: 43 | E25: Millennials | F25: West | G25: Engineer | H25: 185229 | I25: High | J25: Corporate | K25: 42765 | L25: 2017 | M25: 3479 days
A26: CUST0025 | B26: Cindy Parks | C26: Female | D26: 34 | E26: Millennials | F26: North | G26: Student | H26: 97129 | I26: Medium | J26: Retail | K26: 43718 | L26: 2019 | M26: 2526 days
A27: CUST0026 | B27: Charles Fields | C27: Female | D27: 57 | E27: Gen X | F27: South | G27: Doctor | H27: 60042 | I27: Low | J27: Corporate | K27: 44469 | L27: 2021 | M27: 1775 days
A28: CUST0027 | B28: Michael Murray MD | C28: Female | D28: 50 | E28: Gen X | F28: West | G28: Banker | H28: 81665 | I28: Medium | J28: Private | K28: 42607 | L28: 2016 | M28: 3637 days
A29: CUST0028 | B29: Edward Haynes | C29: Female | D29: 26 | E29: Gen z | F29: North | G29: Student | H29: 136953 | I29: Medium | J29: Retail | K29: 43698 | L29: 2019 | M29: 2546 days
A30: CUST0029 | B30: James Allen | C30: Female | D30: 60 | E30: Gen X | F30: South | G30: Engineer | H30: 178448 | I30: High | J30: Private | K30: 44834 | L30: 2022 | M30: 1410 days
A31: CUST0030 | B31: Angela Robinson | C31: Female | D31: 71 | E31: Boomers | F31: South | G31: Student | H31: 165271 | I31: High | J31: Retail | K31: 44109 | L31: 2020 | M31: 2135 days
A32: CUST0031 | B32: Michelle Day | C32: Male | D32: 65 | E32: Boomers | F32: East | G32: Doctor | H32: 138533 | I32: Medium | J32: Corporate | K32: 42742 | L32: 2017 | M32: 3502 days
A33: CUST0032 | B33: Steven Walker | C33: Male | D33: 56 | E33: Gen X | F33: North | G33: Retired | H33: 93781 | I33: Medium | J33: Corporate | K33: 42565 | L33: 2016 | M33: 3679 days
A34: CUST0033 | B34: Lindsey Christensen | C34: Female | D34: 46 | E34: Gen X | F34: North | G34: Engineer | H34: 86262 | I34: Medium | J34: Retail | K34: 43698 | L34: 2019 | M34: 2546 days
A35: CUST0034 | B35: Brooke Carlson | C35: Female | D35: 59 | E35: Gen X | F35: West | G35: Student | H35: 66600 | I35: Low | J35: Corporate | K35: 44513 | L35: 2021 | M35: 1731 days
A36: CUST0035 | B36: Kevin Marshall | C36: Female | D36: 72 | E36: Boomers | F36: East | G36: Banker | H36: 96898 | I36: Medium | J36: Corporate | K36: 42533 | L36: 2016 | M36: 3711 days
... A501: CUST0500 | B501: Olivia Barton | C501: Female | D501: 63 | E501: Boomers | F501: South | G501: Student | H501: 21969 | I501: Low | J501: Corporate | K501: 45488 | L501: 2024 | M501: 756 days

Sheet Customers Account
A1: CustomerID | B1: AccountID | C1: Name | D1: Gender | E1: Age | F1: Age Bracket | G1: Region | H1: Occupation | I1: Join Date | J1: Join Year | K1: Customer Duration | L1: Income | M1: Income Segment | N1: Customer Segment | O1: Account Type | P1: Open Date | Q1: Balance | R1: Credit Score | S1: Credit Score Bracket | T1: Loan Amount | U1: Loan Status
A2: CUST0305 | B2: ACC00001 | C2: Erica Perez | D2: Female | E2: 46 | F2: Gen X | G2: West | H2: Trader | I2: 43041 | J2: 2017 | K2: 3203 days | L2: 29078 | M2: Low | N2: Corporate | O2: Checking | P2: 43258 | Q2: 363265 | R2: 698 | S2: =IF(Linked[[#This Row],[Credit Score]]<=579,"Poor",IF(Linked[[#This Row],[Credit Score]]<=669,"Fair",IF(Linked[[#This Row],[Credit Score]]<=739,"Good",IF(Linked[[#This Row],[Credit Score]]<=799,"Very Good",IF(Linked[[#This Row],[Credit Score]]>=800,"Excellent"))))) -> Good | T2: 0
A3: CUST0305 | B3: ACC00185 | C3: Erica Perez | D3: Female | E3: 46 | F3: Gen X | G3: West | H3: Trader | I3: 43041 | J3: 2017 | K3: 3203 days | L3: 29078 | M3: Low | N3: Corporate | O3: Savings | P3: 44094 | Q3: 398834 | R3: 304 | S3: =IF(Linked[[#This Row],[Credit Score]]<=579,"Poor",IF(Linked[[#This Row],[Credit Score]]<=669,"Fair",IF(Linked[[#This Row],[Credit Score]]<=739,"Good",IF(Linked[[#This Row],[Credit Score]]<=799,"Very Good",IF(Linked[[#This Row],[Credit Score]]>=800,"Excellent"))))) -> Poor | T3: 0
A4: CUST0001 | B4: ACC00461 | C4: Mrs. Deborah Dominguez MD | D4: Male | E4: 38 | F4: Millennials | G4: North | H4: Doctor | I4: 45041 | J4: 2023 | K4: 1203 days | L4: 191672 | M4: High | N4: Retail | O4: Savings | P4: 45360 | Q4: 370180 | R4: 344 | S4: =IF(Linked[[#This Row],[Credit Score]]<=579,"Poor",IF(Linked[[#This Row],[Credit Score]]<=669,"Fair",IF(Linked[[#This Row],[Credit Score]]<=739,"Good",IF(Linked[[#This Row],[Credit Score]]<=799,"Very Good",IF(Linked[[#This Row],[Credit Score]]>=800,"Excellent"))))) -> Poor | T4: 0
A5: CUST0319 | B5: ACC00002 | C5: Reginald Tapia | D5: Male | E5: 57 | F5: Gen X | G5: East | H5: Retired | I5: 43637 | J5: 2019 | K5: 2607 days | L5: 122215 | M5: Medium | N5: Private | O5: Savings | P5: 45670 | Q5: 282169 | R5: 405 | S5: =IF(Linked[[#This Row],[Credit Score]]<=579,"Poor",IF(Linked[[#This Row],[Credit Score]]<=669,"Fair",IF(Linked[[#This Row],[Credit Score]]<=739,"Good",IF(Linked[[#This Row],[Credit Score]]<=799,"Very Good",IF(Linked[[#This Row],[Credit Score]]>=800,"Excellent"))))) -> Poor | T5: 0
A6: CUST0319 | B6: ACC00026 | C6: Reginald Tapia | D6: Male | E6: 57 | F6: Gen X | G6: East | H6: Retired | I6: 43637 | J6: 2019 | K6: 2607 days | L6: 122215 | M6: Medium | N6: Private | O6: Savings | P6: 43851 | Q6: 97493 | R6: 528 | S6: =IF(Linked[[#This Row],[Credit Score]]<=579,"Poor",IF(Linked[[#This Row],[Credit Score]]<=669,"Fair",IF(Linked[[#This Row],[Credit Score]]<=739,"Good",IF(Linked[[#This Row],[Credit Score]]<=799,"Very Good",IF(Linked[[#This Row],[Credit Score]]>=800,"Excellent"))))) -> Poor | T6: 0
A7: CUST0319 | B7: ACC00249 | C7: Reginald Tapia | D7: Male | E7: 57 | F7: Gen X | G7: East | H7: Retired | I7: 43637 | J7: 2019 | K7: 2607 days | L7: 122215 | M7: Medium | N7: Private | O7: Savings | P7: 42662 | Q7: 357574 | R7: 546 | S7: =IF(Linked[[#This Row],[Credit Score]]<=579,"Poor",IF(Linked[[#This Row],[Credit Score]]<=669,"Fair",IF(Linked[[#This Row],[Credit Score]]<=739,"Good",IF(Linked[[#This Row],[Credit Score]]<=799,"Very Good",IF(Linked[[#This Row],[Credit Score]]>=800,"Excellent"))))) -> Poor | T7: 0 | U7: Approved
A8: CUST0002 | B8: ACC00225 | C8: Erin Martinez | D8: Female | E8: 49 | F8: Gen X | G8: East | H8: Trader | I8: 44331 | J8: 2021 | K8: 1913 days | L8: 186472 | M8: High | N8: Corporate | O8: CreditCard | P8: 44739 | Q8: 40142 | R8: 541 | S8: =IF(Linked[[#This Row],[Credit Score]]<=579,"Poor",IF(Linked[[#This Row],[Credit Score]]<=669,"Fair",IF(Linked[[#This Row],[Credit Score]]<=739,"Good",IF(Linked[[#This Row],[Credit Score]]<=799,"Very Good",IF(Linked[[#This Row],[Credit Score]]>=800,"Excellent"))))) -> Poor | T8: 0 | U8: Default
A9: CUST0366 | B9: ACC00003 | C9: Gregory Lee | D9: Male | E9: 45 | F9: Gen X | G9: East | H9: Trader | I9: 43773 | J9: 2019 | K9: 2471 days | L9: 36309 | M9: Low | N9: Retail | O9: Savings | P9: 43852 | Q9: 397674 | R9: 570 | S9: =IF(Linked[[#This Row],[Credit Score]]<=579,"Poor",IF(Linked[[#This Row],[Credit Score]]<=669,"Fair",IF(Linked[[#This Row],[Credit Score]]<=739,"Good",IF(Linked[[#This Row],[Credit Score]]<=799,"Very Good",IF(Linked[[#This Row],[Credit Score]]>=800,"Excellent"))))) -> Poor | T9: 0
A10: CUST0366 | B10: ACC00259 | C10: Gregory Lee | D10: Male | E10: 45 | F10: Gen X | G10: East | H10: Trader | I10: 43773 | J10: 2019 | K10: 2471 days | L10: 36309 | M10: Low | N10: Retail | O10: Checking | P10: 45597 | Q10: 266378 | R10: 634 | S10: =IF(Linked[[#This Row],[Credit Score]]<=579,"Poor",IF(Linked[[#This Row],[Credit Score]]<=669,"Fair",IF(Linked[[#This Row],[Credit Score]]<=739,"Good",IF(Linked[[#This Row],[Credit Score]]<=799,"Very Good",IF(Linked[[#This Row],[Credit Score]]>=800,"Excellent"))))) -> Fair | T10: 0
A11: CUST0366 | B11: ACC00350 | C11: Gregory Lee | D11: Male | E11: 45 | F11: Gen X | G11: East | H11: Trader | I11: 43773 | J11: 2019 | K11: 2471 days | L11: 36309 | M11: Low | N11: Retail | O11: Savings | P11: 43800 | Q11: 282140 | R11: 756 | S11: =IF(Linked[[#This Row],[Credit Score]]<=579,"Poor",IF(Linked[[#This Row],[Credit Score]]<=669,"Fair",IF(Linked[[#This Row],[Credit Score]]<=739,"Good",IF(Linked[[#This Row],[Credit Score]]<=799,"Very Good",IF(Linked[[#This Row],[Credit Score]]>=800,"Excellent"))))) -> Very Good | T11: 0 | U11: Approved
A12: CUST0211 | B12: ACC00004 | C12: Ryan Mccormick | D12: Male | E12: 34 | F12: Millennials | G12: North | H12: Doctor | I12: 43881 | J12: 2020 | K12: 2363 days | L12: 148386 | M12: High | N12: Corporate | O12: Savings | P12: 44837 | Q12: 63610 | R12: 802 | S12: =IF(Linked[[#This Row],[Credit Score]]<=579,"Poor",IF(Linked[[#This Row],[Credit Score]]<=669,"Fair",IF(Linked[[#This Row],[Credit Score]]<=739,"Good",IF(Linked[[#This Row],[Credit Score]]<=799,"Very Good",IF(Linked[[#This Row],[Credit Score]]>=800,"Excellent"))))) -> Excellent | T12: 401875 | U12: Rejected
A13: CUST0211 | B13: ACC00396 | C13: Ryan Mccormick | D13: Male | E13: 34 | F13: Millennials | G13: North | H13: Doctor | I13: 43881 | J13: 2020 | K13: 2363 days | L13: 148386 | M13: High | N13: Corporate | O13: CreditCard | P13: 45320 | Q13: 232654 | R13: 633 | S13: =IF(Linked[[#This Row],[Credit Score]]<=579,"Poor",IF(Linked[[#This Row],[Credit Score]]<=669,"Fair",IF(Linked[[#This Row],[Credit Score]]<=739,"Good",IF(Linked[[#This Row],[Credit Score]]<=799,"Very Good",IF(Linked[[#This Row],[Credit Score]]>=800,"Excellent"))))) -> Fair | T13: 0
A14: CUST0004 | B14: ACC00468 | C14: Candice Palmer | D14: Male | E14: 50 | F14: Gen X | G14: North | H14: Banker | I14: 44494 | J14: 2021 | K14: 1750 days | L14: 142744 | M14: High | N14: Retail | O14: Checking | P14: 42867 | Q14: 128216 | R14: 849 | S14: =IF(Linked[[#This Row],[Credit Score]]<=579,"Poor",IF(Linked[[#This Row],[Credit Score]]<=669,"Fair",IF(Linked[[#This Row],[Credit Score]]<=739,"Good",IF(Linked[[#This Row],[Credit Score]]<=799,"Very Good",IF(Linked[[#This Row],[Credit Score]]>=800,"Excellent"))))) -> Excellent | T14: 0
A15: CUST0406 | B15: ACC00005 | C15: Katherine Freeman | D15: Female | E15: 28 | F15: Gen z | G15: East | H15: Retired | I15: 44902 | J15: 2022 | K15: 1342 days | L15: 39975 | M15: Low | N15: Corporate | O15: Savings | P15: 44039 | Q15: 70843 | R15: 824 | S15: =IF(Linked[[#This Row],[Credit Score]]<=579,"Poor",IF(Linked[[#This Row],[Credit Score]]<=669,"Fair",IF(Linked[[#This Row],[Credit Score]]<=739,"Good",IF(Linked[[#This Row],[Credit Score]]<=799,"Very Good",IF(Linked[[#This Row],[Credit Score]]>=800,"Excellent"))))) -> Excellent | T15: 458505
A16: CUST0005 | B16: ACC00224 | C16: Sandra Davis | D16: Male | E16: 20 | F16: Gen z | G16: West | H16: Student | I16: 43309 | J16: 2018 | K16: 2935 days | L16: 109431 | M16: Medium | N16: Corporate | O16: Checking | P16: 42503 | Q16: 163202 | R16: 491 | S16: =IF(Linked[[#This Row],[Credit Score]]<=579,"Poor",IF(Linked[[#This Row],[Credit Score]]<=669,"Fair",IF(Linked[[#This Row],[Credit Score]]<=739,"Good",IF(Linked[[#This Row],[Credit Score]]<=799,"Very Good",IF(Linked[[#This Row],[Credit Score]]>=800,"Excellent"))))) -> Poor | T16: 0
A17: CUST0152 | B17: ACC00006 | C17: Eric Gomez | D17: Male | E17: 38 | F17: Millennials | G17: East | H17: Retired | I17: 43409 | J17: 2018 | K17: 2835 days | L17: 177732 | M17: High | N17: Corporate | O17: Checking | P17: 44185 | Q17: 107237 | R17: 331 | S17: =IF(Linked[[#This Row],[Credit Score]]<=579,"Poor",IF(Linked[[#This Row],[Credit Score]]<=669,"Fair",IF(Linked[[#This Row],[Credit Score]]<=739,"Good",IF(Linked[[#This Row],[Credit Score]]<=799,"Very Good",IF(Linked[[#This Row],[Credit Score]]>=800,"Excellent"))))) -> Poor | T17: 163666
A18: CUST0152 | B18: ACC00112 | C18: Eric Gomez | D18: Male | E18: 38 | F18: Millennials | G18: East | H18: Retired | I18: 43409 | J18: 2018 | K18: 2835 days | L18: 177732 | M18: High | N18: Corporate | O18: CreditCard | P18: 43077 | Q18: 375197 | R18: 567 | S18: =IF(Linked[[#This Row],[Credit Score]]<=579,"Poor",IF(Linked[[#This Row],[Credit Score]]<=669,"Fair",IF(Linked[[#This Row],[Credit Score]]<=739,"Good",IF(Linked[[#This Row],[Credit Score]]<=799,"Very Good",IF(Linked[[#This Row],[Credit Score]]>=800,"Excellent"))))) -> Poor | T18: 0
A19: CUST0152 | B19: ACC00204 | C19: Eric Gomez | D19: Male | E19: 38 | F19: Millennials | G19: East | H19: Retired | I19: 43409 | J19: 2018 | K19: 2835 days | L19: 177732 | M19: High | N19: Corporate | O19: Checking | P19: 45602 | Q19: 333840 | R19: 428 | S19: =IF(Linked[[#This Row],[Credit Score]]<=579,"Poor",IF(Linked[[#This Row],[Credit Score]]<=669,"Fair",IF(Linked[[#This Row],[Credit Score]]<=739,"Good",IF(Linked[[#This Row],[Credit Score]]<=799,"Very Good",IF(Linked[[#This Row],[Credit Score]]>=800,"Excellent"))))) -> Poor | T19: 0
A20: CUST0109 | B20: ACC00007 | C20: Emily Scott | D20: Female | E20: 29 | F20: Millennials | G20: North | H20: Engineer | I20: 44077 | J20: 2020 | K20: 2167 days | L20: 131785 | M20: Medium | N20: Corporate | O20: CreditCard | P20: 44160 | Q20: 477177 | R20: 692 | S20: =IF(Linked[[#This Row],[Credit Score]]<=579,"Poor",IF(Linked[[#This Row],[Credit Score]]<=669,"Fair",IF(Linked[[#This Row],[Credit Score]]<=739,"Good",IF(Linked[[#This Row],[Credit Score]]<=799,"Very Good",IF(Linked[[#This Row],[Credit Score]]>=800,"Excellent"))))) -> Good | T20: 120819
A21: CUST0109 | B21: ACC00362 | C21: Emily Scott | D21: Female | E21: 29 | F21: Millennials | G21: North | H21: Engineer | I21: 44077 | J21: 2020 | K21: 2167 days | L21: 131785 | M21: Medium | N21: Corporate | O21: CreditCard | P21: 43869 | Q21: 207574 | R21: 803 | S21: =IF(Linked[[#This Row],[Credit Score]]<=579,"Poor",IF(Linked[[#This Row],[Credit Score]]<=669,"Fair",IF(Linked[[#This Row],[Credit Score]]<=739,"Good",IF(Linked[[#This Row],[Credit Score]]<=799,"Very Good",IF(Linked[[#This Row],[Credit Score]]>=800,"Excellent"))))) -> Excellent | T21: 0
A22: CUST0007 | B22: ACC00154 | C22: Tyler Fischer | D22: Male | E22: 42 | F22: Millennials | G22: North | H22: Engineer | I22: 43026 | J22: 2017 | K22: 3218 days | L22: 87364 | M22: Medium | N22: Corporate | O22: CreditCard | P22: 44895 | Q22: 439529 | R22: 587 | S22: =IF(Linked[[#This Row],[Credit Score]]<=579,"Poor",IF(Linked[[#This Row],[Credit Score]]<=669,"Fair",IF(Linked[[#This Row],[Credit Score]]<=739,"Good",IF(Linked[[#This Row],[Credit Score]]<=799,"Very Good",IF(Linked[[#This Row],[Credit Score]]>=800,"Excellent"))))) -> Fair | T22: 0
A23: CUST0076 | B23: ACC00008 | C23: Pamela Johnson | D23: Female | E23: 70 | F23: Boomers | G23: West | H23: Trader | I23: 42917 | J23: 2017 | K23: 3327 days | L23: 172826 | M23: High | N23: Retail | O23: Checking | P23: 45487 | Q23: 180903 | R23: 339 | S23: =IF(Linked[[#This Row],[Credit Score]]<=579,"Poor",IF(Linked[[#This Row],[Credit Score]]<=669,"Fair",IF(Linked[[#This Row],[Credit Score]]<=739,"Good",IF(Linked[[#This Row],[Credit Score]]<=799,"Very Good",IF(Linked[[#This Row],[Credit Score]]>=800,"Excellent"))))) -> Poor | T23: 0
A24: CUST0076 | B24: ACC00238 | C24: Pamela Johnson | D24: Female | E24: 70 | F24: Boomers | G24: West | H24: Trader | I24: 42917 | J24: 2017 | K24: 3327 days | L24: 172826 | M24: High | N24: Retail | O24: Checking | P24: 42353 | Q24: 249664 | R24: 536 | S24: =IF(Linked[[#This Row],[Credit Score]]<=579,"Poor",IF(Linked[[#This Row],[Credit Score]]<=669,"Fair",IF(Linked[[#This Row],[Credit Score]]<=739,"Good",IF(Linked[[#This Row],[Credit Score]]<=799,"Very Good",IF(Linked[[#This Row],[Credit Score]]>=800,"Excellent"))))) -> Poor | T24: 0
A25: CUST0076 | B25: ACC00411 | C25: Pamela Johnson | D25: Female | E25: 70 | F25: Boomers | G25: West | H25: Trader | I25: 42917 | J25: 2017 | K25: 3327 days | L25: 172826 | M25: High | N25: Retail | O25: Checking | P25: 44267 | Q25: 112701 | R25: 540 | S25: =IF(Linked[[#This Row],[Credit Score]]<=579,"Poor",IF(Linked[[#This Row],[Credit Score]]<=669,"Fair",IF(Linked[[#This Row],[Credit Score]]<=739,"Good",IF(Linked[[#This Row],[Credit Score]]<=799,"Very Good",IF(Linked[[#This Row],[Credit Score]]>=800,"Excellent"))))) -> Poor | T25: 0
A26: CUST0008 | B26: ACC00305 | C26: William Horton | D26: Male | E26: 59 | F26: Gen X | G26: North | H26: Engineer | I26: 45448 | J26: 2024 | K26: 796 days | L26: 144988 | M26: High | N26: Retail | O26: CreditCard | P26: 44584 | Q26: 389763 | R26: 444 | S26: =IF(Linked[[#This Row],[Credit Score]]<=579,"Poor",IF(Linked[[#This Row],[Credit Score]]<=669,"Fair",IF(Linked[[#This Row],[Credit Score]]<=739,"Good",IF(Linked[[#This Row],[Credit Score]]<=799,"Very Good",IF(Linked[[#This Row],[Credit Score]]>=800,"Excellent"))))) -> Poor | T26: 0 | U26: Default
A27: CUST0008 | B27: ACC00340 | C27: William Horton | D27: Male | E27: 59 | F27: Gen X | G27: North | H27: Engineer | I27: 45448 | J27: 2024 | K27: 796 days | L27: 144988 | M27: High | N27: Retail | O27: CreditCard | P27: 44887 | Q27: 101158 | R27: 472 | S27: =IF(Linked[[#This Row],[Credit Score]]<=579,"Poor",IF(Linked[[#This Row],[Credit Score]]<=669,"Fair",IF(Linked[[#This Row],[Credit Score]]<=739,"Good",IF(Linked[[#This Row],[Credit Score]]<=799,"Very Good",IF(Linked[[#This Row],[Credit Score]]>=800,"Excellent"))))) -> Poor | T27: 0
A28: CUST0030 | B28: ACC00009 | C28: Angela Robinson | D28: Female | E28: 71 | F28: Boomers | G28: South | H28: Student | I28: 44109 | J28: 2020 | K28: 2135 days | L28: 165271 | M28: High | N28: Retail | O28: CreditCard | P28: 42340 | Q28: 174499 | R28: 517 | S28: =IF(Linked[[#This Row],[Credit Score]]<=579,"Poor",IF(Linked[[#This Row],[Credit Score]]<=669,"Fair",IF(Linked[[#This Row],[Credit Score]]<=739,"Good",IF(Linked[[#This Row],[Credit Score]]<=799,"Very Good",IF(Linked[[#This Row],[Credit Score]]>=800,"Excellent"))))) -> Poor | T28: 0
A29: CUST0314 | B29: ACC00010 | C29: Kenneth Vasquez | D29: Male | E29: 34 | F29: Millennials | G29: West | H29: Doctor | I29: 44714 | J29: 2022 | K29: 1530 days | L29: 145150 | M29: High | N29: Retail | O29: Loan | P29: 45493 | Q29: 487025 | R29: 381 | S29: =IF(Linked[[#This Row],[Credit Score]]<=579,"Poor",IF(Linked[[#This Row],[Credit Score]]<=669,"Fair",IF(Linked[[#This Row],[Credit Score]]<=739,"Good",IF(Linked[[#This Row],[Credit Score]]<=799,"Very Good",IF(Linked[[#This Row],[Credit Score]]>=800,"Excellent"))))) -> Poor | T29: 0
A30: CUST0314 | B30: ACC00176 | C30: Kenneth Vasquez | D30: Male | E30: 34 | F30: Millennials | G30: West | H30: Doctor | I30: 44714 | J30: 2022 | K30: 1530 days | L30: 145150 | M30: High | N30: Retail | O30: Savings | P30: 44383 | Q30: 36320 | R30: 810 | S30: =IF(Linked[[#This Row],[Credit Score]]<=579,"Poor",IF(Linked[[#This Row],[Credit Score]]<=669,"Fair",IF(Linked[[#This Row],[Credit Score]]<=739,"Good",IF(Linked[[#This Row],[Credit Score]]<=799,"Very Good",IF(Linked[[#This Row],[Credit Score]]>=800,"Excellent"))))) -> Excellent | T30: 0 | U30: Default
A31: CUST0314 | B31: ACC00430 | C31: Kenneth Vasquez | D31: Male | E31: 34 | F31: Millennials | G31: West | H31: Doctor | I31: 44714 | J31: 2022 | K31: 1530 days | L31: 145150 | M31: High | N31: Retail | O31: Checking | P31: 44014 | Q31: 379747 | R31: 316 | S31: =IF(Linked[[#This Row],[Credit Score]]<=579,"Poor",IF(Linked[[#This Row],[Credit Score]]<=669,"Fair",IF(Linked[[#This Row],[Credit Score]]<=739,"Good",IF(Linked[[#This Row],[Credit Score]]<=799,"Very Good",IF(Linked[[#This Row],[Credit Score]]>=800,"Excellent"))))) -> Poor | T31: 0
A32: CUST0486 | B32: ACC00011 | C32: Ronald Craig | D32: Female | E32: 55 | F32: Gen X | G32: East | H32: Retired | I32: 45621 | J32: 2024 | K32: 623 days | L32: 166470 | M32: High | N32: Retail | O32: CreditCard | P32: 45351 | Q32: 130299 | R32: 500 | S32: =IF(Linked[[#This Row],[Credit Score]]<=579,"Poor",IF(Linked[[#This Row],[Credit Score]]<=669,"Fair",IF(Linked[[#This Row],[Credit Score]]<=739,"Good",IF(Linked[[#This Row],[Credit Score]]<=799,"Very Good",IF(Linked[[#This Row],[Credit Score]]>=800,"Excellent"))))) -> Poor | T32: 0
A33: CUST0486 | B33: ACC00336 | C33: Ronald Craig | D33: Female | E33: 55 | F33: Gen X | G33: East | H33: Retired | I33: 45621 | J33: 2024 | K33: 623 days | L33: 166470 | M33: High | N33: Retail | O33: CreditCard | P33: 44222 | Q33: 427876 | R33: 496 | S33: =IF(Linked[[#This Row],[Credit Score]]<=579,"Poor",IF(Linked[[#This Row],[Credit Score]]<=669,"Fair",IF(Linked[[#This Row],[Credit Score]]<=739,"Good",IF(Linked[[#This Row],[Credit Score]]<=799,"Very Good",IF(Linked[[#This Row],[Credit Score]]>=800,"Excellent"))))) -> Poor | T33: 0
A34: CUST0486 | B34: ACC00393 | C34: Ronald Craig | D34: Female | E34: 55 | F34: Gen X | G34: East | H34: Retired | I34: 45621 | J34: 2024 | K34: 623 days | L34: 166470 | M34: High | N34: Retail | O34: CreditCard | P34: 43220 | Q34: 434825 | R34: 613 | S34: =IF(Linked[[#This Row],[Credit Score]]<=579,"Poor",IF(Linked[[#This Row],[Credit Score]]<=669,"Fair",IF(Linked[[#This Row],[Credit Score]]<=739,"Good",IF(Linked[[#This Row],[Credit Score]]<=799,"Very Good",IF(Linked[[#This Row],[Credit Score]]>=800,"Excellent"))))) -> Fair | T34: 0
A35: CUST0117 | B35: ACC00012 | C35: Heidi Sharp | D35: Male | E35: 65 | F35: Boomers | G35: North | H35: Student | I35: 45706 | J35: 2025 | K35: 538 days | L35: 94553 | M35: Medium | N35: Retail | O35: Checking | P35: 44010 | Q35: 431722 | R35: 746 | S35: =IF(Linked[[#This Row],[Credit Score]]<=579,"Poor",IF(Linked[[#This Row],[Credit Score]]<=669,"Fair",IF(Linked[[#This Row],[Credit Score]]<=739,"Good",IF(Linked[[#This Row],[Credit Score]]<=799,"Very Good",IF(Linked[[#This Row],[Credit Score]]>=800,"Excellent"))))) -> Very Good | T35: 278365
A36: CUST0117 | B36: ACC00196 | C36: Heidi Sharp | D36: Male | E36: 65 | F36: Boomers | G36: North | H36: Student | I36: 45706 | J36: 2025 | K36: 538 days | L36: 94553 | M36: Medium | N36: Retail | O36: Savings | P36: 42688 | Q36: 422132 | R36: 650 | S36: =IF(Linked[[#This Row],[Credit Score]]<=579,"Poor",IF(Linked[[#This Row],[Credit Score]]<=669,"Fair",IF(Linked[[#This Row],[Credit Score]]<=739,"Good",IF(Linked[[#This Row],[Credit Score]]<=799,"Very Good",IF(Linked[[#This Row],[Credit Score]]>=800,"Excellent"))))) -> Fair | T36: 0
A37: CUST0117 | B37: ACC00478 | C37: Heidi Sharp | D37: Male | E37: 65 | F37: Boomers | G37: North | H37: Student | I37: 45706 | J37: 2025 | K37: 538 days | L37: 94553 | M37: Medium | N37: Retail | O37: CreditCard | P37: 42968 | Q37: 102476 | R37: 816 | S37: =IF(Linked[[#This Row],[Credit Score]]<=579,"Poor",IF(Linked[[#This Row],[Credit Score]]<=669,"Fair",IF(Linked[[#This Row],[Credit Score]]<=739,"Good",IF(Linked[[#This Row],[Credit Score]]<=799,"Very Good",IF(Linked[[#This Row],[Credit Score]]>=800,"Excellent"))))) -> Excellent | T37: 0
A38: CUST0012 | B38: ACC00355 | C38: Michael Richard | D38: Male | E38: 57 | F38: Gen X | G38: West | H38: Trader | I38: 45280 | J38: 2023 | K38: 964 days | L38: 144343 | M38: High | N38: Corporate | O38: Savings | P38: 43741 | Q38: 166782 | R38: 746 | S38: =IF(Linked[[#This Row],[Credit Score]]<=579,"Poor",IF(Linked[[#This Row],[Credit Score]]<=669,"Fair",IF(Linked[[#This Row],[Credit Score]]<=739,"Good",IF(Linked[[#This Row],[Credit Score]]<=799,"Very Good",IF(Linked[[#This Row],[Credit Score]]>=800,"Excellent"))))) -> Very Good | T38: 0
A39: CUST0415 | B39: ACC00013 | C39: Kyle Rodriguez | D39: Male | E39: 45 | F39: Gen X | G39: South | H39: Retired | I39: 45884 | J39: 2025 | K39: 360 days | L39: 145932 | M39: High | N39: Corporate | O39: Checking | P39: 45860 | Q39: 5668 | R39: 727 | S39: =IF(Linked[[#This Row],[Credit Score]]<=579,"Poor",IF(Linked[[#This Row],[Credit Score]]<=669,"Fair",IF(Linked[[#This Row],[Credit Score]]<=739,"Good",IF(Linked[[#This Row],[Credit Score]]<=799,"Very Good",IF(Linked[[#This Row],[Credit Score]]>=800,"Excellent"))))) -> Good | T39: 0 | U39: Approved
A40: CUST0356 | B40: ACC00014 | C40: Tyler Harris | D40: Male | E40: 67 | F40: Boomers | G40: West | H40: Banker | I40: 43374 | J40: 2018 | K40: 2870 days | L40: 134994 | M40: Medium | N40: Corporate | O40: Checking | P40: 44587 | Q40: 222542 | R40: 337 | S40: =IF(Linked[[#This Row],[Credit Score]]<=579,"Poor",IF(Linked[[#This Row],[Credit Score]]<=669,"Fair",IF(Linked[[#This Row],[Credit Score]]<=739,"Good",IF(Linked[[#This Row],[Credit Score]]<=799,"Very Good",IF(Linked[[#This Row],[Credit Score]]>=800,"Excellent"))))) -> Poor | T40: 18569
A41: CUST0356 | B41: ACC00089 | C41: Tyler Harris | D41: Male | E41: 67 | F41: Boomers | G41: West | H41: Banker | I41: 43374 | J41: 2018 | K41: 2870 days | L41: 134994 | M41: Medium | N41: Corporate | O41: CreditCard | P41: 43262 | Q41: 61753 | R41: 393 | S41: =IF(Linked[[#This Row],[Credit Score]]<=579,"Poor",IF(Linked[[#This Row],[Credit Score]]<=669,"Fair",IF(Linked[[#This Row],[Credit Score]]<=739,"Good",IF(Linked[[#This Row],[Credit Score]]<=799,"Very Good",IF(Linked[[#This Row],[Credit Score]]>=800,"Excellent"))))) -> Poor | T41: 146835
A42: CUST0192 | B42: ACC00015 | C42: Kim Hubbard | D42: Male | E42: 54 | F42: Gen X | G42: South | H42: Engineer | I42: 45891 | J42: 2025 | K42: 353 days | L42: 117768 | M42: Medium | N42: Retail | O42: Savings | P42: 45438 | Q42: 178267 | R42: 510 | S42: =IF(Linked[[#This Row],[Credit Score]]<=579,"Poor",IF(Linked[[#This Row],[Credit Score]]<=669,"Fair",IF(Linked[[#This Row],[Credit Score]]<=739,"Good",IF(Linked[[#This Row],[Credit Score]]<=799,"Very Good",IF(Linked[[#This Row],[Credit Score]]>=800,"Excellent"))))) -> Poor | T42: 0
A43: CUST0192 | B43: ACC00087 | C43: Kim Hubbard | D43: Male | E43: 54 | F43: Gen X | G43: South | H43: Engineer | I43: 45891 | J43: 2025 | K43: 353 days | L43: 117768 | M43: Medium | N43: Retail | O43: Savings | P43: 43238 | Q43: 459952 | R43: 797 | S43: =IF(Linked[[#This Row],[Credit Score]]<=579,"Poor",IF(Linked[[#This Row],[Credit Score]]<=669,"Fair",IF(Linked[[#This Row],[Credit Score]]<=739,"Good",IF(Linked[[#This Row],[Credit Score]]<=799,"Very Good",IF(Linked[[#This Row],[Credit Score]]>=800,"Excellent"))))) -> Very Good | T43: 0 | U43: Approved
A44: CUST0192 | B44: ACC00247 | C44: Kim Hubbard | D44: Male | E44: 54 | F44: Gen X | G44: South | H44: Engineer | I44: 45891 | J44: 2025 | K44: 353 days | L44: 117768 | M44: Medium | N44: Retail | O44: CreditCard | P44: 42655 | Q44: 465525 | R44: 756 | S44: =IF(Linked[[#This Row],[Credit Score]]<=579,"Poor",IF(Linked[[#This Row],[Credit Score]]<=669,"Fair",IF(Linked[[#This Row],[Credit Score]]<=739,"Good",IF(Linked[[#This Row],[Credit Score]]<=799,"Very Good",IF(Linked[[#This Row],[Credit Score]]>=800,"Excellent"))))) -> Very Good | T44: 0 | U44: Approved
A45: CUST0019 | B45: ACC00016 | C45: Melissa Clark | D45: Female | E45: 40 | F45: Millennials | G45: South | H45: Teacher | I45: 44456 | J45: 2021 | K45: 1788 days | L45: 100435 | M45: Medium | N45: Corporate | O45: Savings | P45: 43064 | Q45: 335377 | R45: 743 | S45: =IF(Linked[[#This Row],[Credit Score]]<=579,"Poor",IF(Linked[[#This Row],[Credit Score]]<=669,"Fair",IF(Linked[[#This Row],[Credit Score]]<=739,"Good",IF(Linked[[#This Row],[Credit Score]]<=799,"Very Good",IF(Linked[[#This Row],[Credit Score]]>=800,"Excellent"))))) -> Very Good | T45: 0
A46: CUST0016 | B46: ACC00359 | C46: Ashlee Baird | D46: Male | E46: 49 | F46: Gen X | G46: South | H46: Banker | I46: 43643 | J46: 2019 | K46: 2601 days | L46: 54636 | M46: Low | N46: Retail | O46: Checking | P46: 44388 | Q46: 470457 | R46: 687 | S46: =IF(Linked[[#This Row],[Credit Score]]<=579,"Poor",IF(Linked[[#This Row],[Credit Score]]<=669,"Fair",IF(Linked[[#This Row],[Credit Score]]<=739,"Good",IF(Linked[[#This Row],[Credit Score]]<=799,"Very Good",IF(Linked[[#This Row],[Credit Score]]>=800,"Excellent"))))) -> Good | T46: 0
A47: CUST0432 | B47: ACC00017 | C47: Zachary Vasquez | D47: Female | E47: 50 | F47: Gen X | G47: East | H47: Trader | I47: 42887 | J47: 2017 | K47: 3357 days | L47: 81367 | M47: Medium | N47: Corporate | O47: Loan | P47: 44333 | Q47: 155489 | R47: 626 | S47: =IF(Linked[[#This Row],[Credit Score]]<=579,"Poor",IF(Linked[[#This Row],[Credit Score]]<=669,"Fair",IF(Linked[[#This Row],[Credit Score]]<=739,"Good",IF(Linked[[#This Row],[Credit Score]]<=799,"Very Good",IF(Linked[[#This Row],[Credit Score]]>=800,"Excellent"))))) -> Fair | T47: 207630
A48: CUST0432 | B48: ACC00165 | C48: Zachary Vasquez | D48: Female | E48: 50 | F48: Gen X | G48: East | H48: Trader | I48: 42887 | J48: 2017 | K48: 3357 days | L48: 81367 | M48: Medium | N48: Corporate | O48: Loan | P48: 43936 | Q48: 307086 | R48: 759 | S48: =IF(Linked[[#This Row],[Credit Score]]<=579,"Poor",IF(Linked[[#This Row],[Credit Score]]<=669,"Fair",IF(Linked[[#This Row],[Credit Score]]<=739,"Good",IF(Linked[[#This Row],[Credit Score]]<=799,"Very Good",IF(Linked[[#This Row],[Credit Score]]>=800,"Excellent"))))) -> Very Good | T48: 0
A49: CUST0432 | B49: ACC00317 | C49: Zachary Vasquez | D49: Female | E49: 50 | F49: Gen X | G49: East | H49: Trader | I49: 42887 | J49: 2017 | K49: 3357 days | L49: 81367 | M49: Medium | N49: Corporate | O49: Savings | P49: 43006 | Q49: 295809 | R49: 489 | S49: =IF(Linked[[#This Row],[Credit Score]]<=579,"Poor",IF(Linked[[#This Row],[Credit Score]]<=669,"Fair",IF(Linked[[#This Row],[Credit Score]]<=739,"Good",IF(Linked[[#This Row],[Credit Score]]<=799,"Very Good",IF(Linked[[#This Row],[Credit Score]]>=800,"Excellent"))))) -> Poor | T49: 0
A50: CUST0017 | B50: ACC00215 | C50: Michael Conner | D50: Female | E50: 64 | F50: Boomers | G50: South | H50: Banker | I50: 44375 | J50: 2021 | K50: 1869 days | L50: 199352 | M50: High | N50: Retail | O50: CreditCard | P50: 43732 | Q50: 353076 | R50: 601 | S50: =IF(Linked[[#This Row],[Credit Score]]<=579,"Poor",IF(Linked[[#This Row],[Credit Score]]<=669,"Fair",IF(Linked[[#This Row],[Credit Score]]<=739,"Good",IF(Linked[[#This Row],[Credit Score]]<=799,"Very Good",IF(Linked[[#This Row],[Credit Score]]>=800,"Excellent"))))) -> Fair | T50: 0 | U50: Default
A51: CUST0173 | B51: ACC00018 | C51: David Wilson | D51: Male | E51: 21 | F51: Gen z | G51: South | H51: Trader | I51: 44501 | J51: 2021 | K51: 1743 days | L51: 172499 | M51: High | N51: Corporate | O51: CreditCard | P51: 44007 | Q51: 344126 | R51: 526 | S51: =IF(Linked[[#This Row],[Credit Score]]<=579,"Poor",IF(Linked[[#This Row],[Credit Score]]<=669,"Fair",IF(Linked[[#This Row],[Credit Score]]<=739,"Good",IF(Linked[[#This Row],[Credit Score]]<=799,"Very Good",IF(Linked[[#This Row],[Credit Score]]>=800,"Excellent"))))) -> Poor | T51: 0
A52: CUST0228 | B52: ACC00019 | C52: Melinda Cunningham | D52: Female | E52: 73 | F52: Boomers | G52: West | H52: Trader | I52: 43479 | J52: 2019 | K52: 2765 days | L52: 135672 | M52: Medium | N52: Corporate | O52: Savings | P52: 44694 | Q52: 106133 | R52: 347 | S52: =IF(Linked[[#This Row],[Credit Score]]<=579,"Poor",IF(Linked[[#This Row],[Credit Score]]<=669,"Fair",IF(Linked[[#This Row],[Credit Score]]<=739,"Good",IF(Linked[[#This Row],[Credit Score]]<=799,"Very Good",IF(Linked[[#This Row],[Credit Score]]>=800,"Excellent"))))) -> Poor | T52: 0 | U52: Rejected
A53: CUST0228 | B53: ACC00141 | C53: Melinda Cunningham | D53: Female | E53: 73 | F53: Boomers | G53: West | H53: Trader | I53: 43479 | J53: 2019 | K53: 2765 days | L53: 135672 | M53: Medium | N53: Corporate | O53: Checking | P53: 44184 | Q53: 369360 | R53: 483 | S53: =IF(Linked[[#This Row],[Credit Score]]<=579,"Poor",IF(Linked[[#This Row],[Credit Score]]<=669,"Fair",IF(Linked[[#This Row],[Credit Score]]<=739,"Good",IF(Linked[[#This Row],[Credit Score]]<=799,"Very Good",IF(Linked[[#This Row],[Credit Score]]>=800,"Excellent"))))) -> Poor | T53: 8681
A54: CUST0350 | B54: ACC00020 | C54: Brandon Fox DDS | D54: Male | E54: 43 | F54: Millennials | G54: South | H54: Teacher | I54: 44926 | J54: 2022 | K54: 1318 days | L54: 90316 | M54: Medium | N54: Corporate | O54: Checking | P54: 43335 | Q54: 272895 | R54: 317 | S54: =IF(Linked[[#This Row],[Credit Score]]<=579,"Poor",IF(Linked[[#This Row],[Credit Score]]<=669,"Fair",IF(Linked[[#This Row],[Credit Score]]<=739,"Good",IF(Linked[[#This Row],[Credit Score]]<=799,"Very Good",IF(Linked[[#This Row],[Credit Score]]>=800,"Excellent"))))) -> Poor | T54: 0
A55: CUST0350 | B55: ACC00064 | C55: Brandon Fox DDS | D55: Male | E55: 43 | F55: Millennials | G55: South | H55: Teacher | I55: 44926 | J55: 2022 | K55: 1318 days | L55: 90316 | M55: Medium | N55: Corporate | O55: Savings | P55: 43714 | Q55: 128128 | R55: 824 | S55: =IF(Linked[[#This Row],[Credit Score]]<=579,"Poor",IF(Linked[[#This Row],[Credit Score]]<=669,"Fair",IF(Linked[[#This Row],[Credit Score]]<=739,"Good",IF(Linked[[#This Row],[Credit Score]]<=799,"Very Good",IF(Linked[[#This Row],[Credit Score]]>=800,"Excellent"))))) -> Excellent | T55: 0
A56: CUST0350 | B56: ACC00441 | C56: Brandon Fox DDS | D56: Male | E56: 43 | F56: Millennials | G56: South | H56: Teacher | I56: 44926 | J56: 2022 | K56: 1318 days | L56: 90316 | M56: Medium | N56: Corporate | O56: Checking | P56: 44015 | Q56: 430917 | R56: 479 | S56: =IF(Linked[[#This Row],[Credit Score]]<=579,"Poor",IF(Linked[[#This Row],[Credit Score]]<=669,"Fair",IF(Linked[[#This Row],[Credit Score]]<=739,"Good",IF(Linked[[#This Row],[Credit Score]]<=799,"Very Good",IF(Linked[[#This Row],[Credit Score]]>=800,"Excellent"))))) -> Poor | T56: 0
A57: CUST0020 | B57: ACC00255 | C57: Janice Scott | D57: Male | E57: 19 | F57: Gen z | G57: South | H57: Engineer | I57: 45058 | J57: 2023 | K57: 1186 days | L57: 148583 | M57: High | N57: Corporate | O57: Savings | P57: 45511 | Q57: 118696 | R57: 490 | S57: =IF(Linked[[#This Row],[Credit Score]]<=579,"Poor",IF(Linked[[#This Row],[Credit Score]]<=669,"Fair",IF(Linked[[#This Row],[Credit Score]]<=739,"Good",IF(Linked[[#This Row],[Credit Score]]<=799,"Very Good",IF(Linked[[#This Row],[Credit Score]]>=800,"Excellent"))))) -> Poor | T57: 372508
A58: CUST0183 | B58: ACC00021 | C58: Victor Thomas | D58: Female | E58: 37 | F58: Millennials | G58: East | H58: Student | I58: 43202 | J58: 2018 | K58: 3042 days | L58: 49241 | M58: Low | N58: Retail | O58: CreditCard | P58: 43980 | Q58: 308362 | R58: 738 | S58: =IF(Linked[[#This Row],[Credit Score]]<=579,"Poor",IF(Linked[[#This Row],[Credit Score]]<=669,"Fair",IF(Linked[[#This Row],[Credit Score]]<=739,"Good",IF(Linked[[#This Row],[Credit Score]]<=799,"Very Good",IF(Linked[[#This Row],[Credit Score]]>=800,"Excellent"))))) -> Good | T58: 0
A59: CUST0183 | B59: ACC00023 | C59: Victor Thomas | D59: Female | E59: 37 | F59: Millennials | G59: East | H59: Student | I59: 43202 | J59: 2018 | K59: 3042 days | L59: 49241 | M59: Low | N59: Retail | O59: Savings | P59: 45186 | Q59: 269496 | R59: 644 | S59: =IF(Linked[[#This Row],[Credit Score]]<=579,"Poor",IF(Linked[[#This Row],[Credit Score]]<=669,"Fair",IF(Linked[[#This Row],[Credit Score]]<=739,"Good",IF(Linked[[#This Row],[Credit Score]]<=799,"Very Good",IF(Linked[[#This Row],[Credit Score]]>=800,"Excellent"))))) -> Fair | T59: 0 | U59: Default
A60: CUST0021 | B60: ACC00149 | C60: Elizabeth Smith | D60: Female | E60: 44 | F60: Millennials | G60: East | H60: Trader | I60: 45414 | J60: 2024 | K60: 830 days | L60: 189269 | M60: High | N60: Retail | O60: CreditCard | P60: 42302 | Q60: 99977 | R60: 476 | S60: =IF(Linked[[#This Row],[Credit Score]]<=579,"Poor",IF(Linked[[#This Row],[Credit Score]]<=669,"Fair",IF(Linked[[#This Row],[Credit Score]]<=739,"Good",IF(Linked[[#This Row],[Credit Score]]<=799,"Very Good",IF(Linked[[#This Row],[Credit Score]]>=800,"Excellent"))))) -> Poor | T60: 0
A61: CUST0021 | B61: ACC00177 | C61: Elizabeth Smith | D61: Female | E61: 44 | F61: Millennials | G61: East | H61: Trader | I61: 45414 | J61: 2024 | K61: 830 days | L61: 189269 | M61: High | N61: Retail | O61: CreditCard | P61: 44086 | Q61: 49170 | R61: 549 | S61: =IF(Linked[[#This Row],[Credit Score]]<=579,"Poor",IF(Linked[[#This Row],[Credit Score]]<=669,"Fair",IF(Linked[[#This Row],[Credit Score]]<=739,"Good",IF(Linked[[#This Row],[Credit Score]]<=799,"Very Good",IF(Linked[[#This Row],[Credit Score]]>=800,"Excellent"))))) -> Poor | T61: 85730
A62: CUST0021 | B62: ACC00364 | C62: Elizabeth Smith | D62: Female | E62: 44 | F62: Millennials | G62: East | H62: Trader | I62: 45414 | J62: 2024 | K62: 830 days | L62: 189269 | M62: High | N62: Retail | O62: Checking | P62: 42545 | Q62: 469890 | R62: 590 | S62: =IF(Linked[[#This Row],[Credit Score]]<=579,"Poor",IF(Linked[[#This Row],[Credit Score]]<=669,"Fair",IF(Linked[[#This Row],[Credit Score]]<=739,"Good",IF(Linked[[#This Row],[Credit Score]]<=799,"Very Good",IF(Linked[[#This Row],[Credit Score]]>=800,"Excellent"))))) -> Fair | T62: 222364
A63: CUST0021 | B63: ACC00475 | C63: Elizabeth Smith | D63: Female | E63: 44 | F63: Millennials | G63: East | H63: Trader | I63: 45414 | J63: 2024 | K63: 830 days | L63: 189269 | M63: High | N63: Retail | O63: CreditCard | P63: 43880 | Q63: 352156 | R63: 587 | S63: =IF(Linked[[#This Row],[Credit Score]]<=579,"Poor",IF(Linked[[#This Row],[Credit Score]]<=669,"Fair",IF(Linked[[#This Row],[Credit Score]]<=739,"Good",IF(Linked[[#This Row],[Credit Score]]<=799,"Very Good",IF(Linked[[#This Row],[Credit Score]]>=800,"Excellent"))))) -> Fair | T63: 0 | U63: Rejected
A64: CUST0113 | B64: ACC00022 | C64: Anthony Ramos | D64: Female | E64: 64 | F64: Boomers | G64: East | H64: Doctor | I64: 42445 | J64: 2016 | K64: 3799 days | L64: 73947 | M64: Low | N64: Private | O64: Savings | P64: 45635 | Q64: 388793 | R64: 486 | S64: =IF(Linked[[#This Row],[Credit Score]]<=579,"Poor",IF(Linked[[#This Row],[Credit Score]]<=669,"Fair",IF(Linked[[#This Row],[Credit Score]]<=739,"Good",IF(Linked[[#This Row],[Credit Score]]<=799,"Very Good",IF(Linked[[#This Row],[Credit Score]]>=800,"Excellent"))))) -> Poor | T64: 258078
A65: CUST0113 | B65: ACC00028 | C65: Anthony Ramos | D65: Female | E65: 64 | F65: Boomers | G65: East | H65: Doctor | I65: 42445 | J65: 2016 | K65: 3799 days | L65: 73947 | M65: Low | N65: Private | O65: CreditCard | P65: 43189 | Q65: 172166 | R65: 487 | S65: =IF(Linked[[#This Row],[Credit Score]]<=579,"Poor",IF(Linked[[#This Row],[Credit Score]]<=669,"Fair",IF(Linked[[#This Row],[Credit Score]]<=739,"Good",IF(Linked[[#This Row],[Credit Score]]<=799,"Very Good",IF(Linked[[#This Row],[Credit Score]]>=800,"Excellent"))))) -> Poor | T65: 0 | U65: Default
A66: CUST0113 | B66: ACC00063 | C66: Anthony Ramos | D66: Female | E66: 64 | F66: Boomers | G66: East | H66: Doctor | I66: 42445 | J66: 2016 | K66: 3799 days | L66: 73947 | M66: Low | N66: Private | O66: Loan | P66: 43721 | Q66: 12356 | R66: 687 | S66: =IF(Linked[[#This Row],[Credit Score]]<=579,"Poor",IF(Linked[[#This Row],[Credit Score]]<=669,"Fair",IF(Linked[[#This Row],[Credit Score]]<=739,"Good",IF(Linked[[#This Row],[Credit Score]]<=799,"Very Good",IF(Linked[[#This Row],[Credit Score]]>=800,"Excellent"))))) -> Good | T66: 0
A67: CUST0022 | B67: ACC00226 | C67: Jodi Burns | D67: Male | E67: 59 | F67: Gen X | G67: East | H67: Retired | I67: 45118 | J67: 2023 | K67: 1126 days | L67: 61844 | M67: Low | N67: Corporate | O67: Checking | P67: 42645 | Q67: 36468 | R67: 437 | S67: =IF(Linked[[#This Row],[Credit Score]]<=579,"Poor",IF(Linked[[#This Row],[Credit Score]]<=669,"Fair",IF(Linked[[#This Row],[Credit Score]]<=739,"Good",IF(Linked[[#This Row],[Credit Score]]<=799,"Very Good",IF(Linked[[#This Row],[Credit Score]]>=800,"Excellent"))))) -> Poor | T67: 0
A68: CUST0481 | B68: ACC00024 | C68: Carolyn Evans | D68: Female | E68: 45 | F68: Gen X | G68: East | H68: Retired | I68: 42411 | J68: 2016 | K68: 3833 days | L68: 152311 | M68: High | N68: Retail | O68: CreditCard | P68: 43146 | Q68: 210124 | R68: 523 | S68: =IF(Linked[[#This Row],[Credit Score]]<=579,"Poor",IF(Linked[[#This Row],[Credit Score]]<=669,"Fair",IF(Linked[[#This Row],[Credit Score]]<=739,"Good",IF(Linked[[#This Row],[Credit Score]]<=799,"Very Good",IF(Linked[[#This Row],[Credit Score]]>=800,"Excellent"))))) -> Poor | T68: 0
A69: CUST0146 | B69: ACC00025 | C69: Veronica Mullins | D69: Male | E69: 22 | F69: Gen z | G69: North | H69: Teacher | I69: 44029 | J69: 2020 | K69: 2215 days | L69: 49257 | M69: Low | N69: Retail | O69: Checking | P69: 42535 | Q69: 88835 | R69: 787 | S69: =IF(Linked[[#This Row],[Credit Score]]<=579,"Poor",IF(Linked[[#This Row],[Credit Score]]<=669,"Fair",IF(Linked[[#This Row],[Credit Score]]<=739,"Good",IF(Linked[[#This Row],[Credit Score]]<=799,"Very Good",IF(Linked[[#This Row],[Credit Score]]>=800,"Excellent"))))) -> Very Good | T69: 485443
A70: CUST0025 | B70: ACC00377 | C70: Cindy Parks | D70: Female | E70: 34 | F70: Millennials | G70: North | H70: Student | I70: 43718 | J70: 2019 | K70: 2526 days | L70: 97129 | M70: Medium | N70: Retail | O70: CreditCard | P70: 43396 | Q70: 232892 | R70: 532 | S70: =IF(Linked[[#This Row],[Credit Score]]<=579,"Poor",IF(Linked[[#This Row],[Credit Score]]<=669,"Fair",IF(Linked[[#This Row],[Credit Score]]<=739,"Good",IF(Linked[[#This Row],[Credit Score]]<=799,"Very Good",IF(Linked[[#This Row],[Credit Score]]>=800,"Excellent"))))) -> Poor | T70: 0
A71: CUST0026 | B71: ACC00277 | C71: Charles Fields | D71: Female | E71: 57 | F71: Gen X | G71: South | H71: Doctor | I71: 44469 | J71: 2021 | K71: 1775 days | L71: 60042 | M71: Low | N71: Corporate | O71: Checking | P71: 42664 | Q71: 207139 | R71: 544 | S71: =IF(Linked[[#This Row],[Credit Score]]<=579,"Poor",IF(Linked[[#This Row],[Credit Score]]<=669,"Fair",IF(Linked[[#This Row],[Credit Score]]<=739,"Good",IF(Linked[[#This Row],[Credit Score]]<=799,"Very Good",IF(Linked[[#This Row],[Credit Score]]>=800,"Excellent"))))) -> Poor | T71: 382411
A72: CUST0116 | B72: ACC00027 | C72: Guy Hughes | D72: Female | E72: 71 | F72: Boomers | G72: South | H72: Student | I72: 45797 | J72: 2025 | K72: 447 days | L72: 69708 | M72: Low | N72: Corporate | O72: Checking | P72: 45203 | Q72: 291071 | R72: 689 | S72: =IF(Linked[[#This Row],[Credit Score]]<=579,"Poor",IF(Linked[[#This Row],[Credit Score]]<=669,"Fair",IF(Linked[[#This Row],[Credit Score]]<=739,"Good",IF(Linked[[#This Row],[Credit Score]]<=799,"Very Good",IF(Linked[[#This Row],[Credit Score]]>=800,"Excellent"))))) -> Good | T72: 196007
A73: CUST0116 | B73: ACC00268 | C73: Guy Hughes | D73: Female | E73: 71 | F73: Boomers | G73: South | H73: Student | I73: 45797 | J73: 2025 | K73: 447 days | L73: 69708 | M73: Low | N73: Corporate | O73: Savings | P73: 44000 | Q73: 303297 | R73: 462 | S73: =IF(Linked[[#This Row],[Credit Score]]<=579,"Poor",IF(Linked[[#This Row],[Credit Score]]<=669,"Fair",IF(Linked[[#This Row],[Credit Score]]<=739,"Good",IF(Linked[[#This Row],[Credit Score]]<=799,"Very Good",IF(Linked[[#This Row],[Credit Score]]>=800,"Excellent"))))) -> Poor | T73: 0
A74: CUST0028 | B74: ACC00208 | C74: Edward Haynes | D74: Female | E74: 26 | F74: Gen z | G74: North | H74: Student | I74: 43698 | J74: 2019 | K74: 2546 days | L74: 136953 | M74: Medium | N74: Retail | O74: CreditCard | P74: 43587 | Q74: 130841 | R74: 732 | S74: =IF(Linked[[#This Row],[Credit Score]]<=579,"Poor",IF(Linked[[#This Row],[Credit Score]]<=669,"Fair",IF(Linked[[#This Row],[Credit Score]]<=739,"Good",IF(Linked[[#This Row],[Credit Score]]<=799,"Very Good",IF(Linked[[#This Row],[Credit Score]]>=800,"Excellent"))))) -> Good | T74: 0
A75: CUST0251 | B75: ACC00029 | C75: Danny Scott | D75: Female | E75: 29 | F75: Millennials | G75: North | H75: Teacher | I75: 45422 | J75: 2024 | K75: 822 days | L75: 124101 | M75: Medium | N75: Corporate | O75: Checking | P75: 43955 | Q75: 101948 | R75: 569 | S75: =IF(Linked[[#This Row],[Credit Score]]<=579,"Poor",IF(Linked[[#This Row],[Credit Score]]<=669,"Fair",IF(Linked[[#This Row],[Credit Score]]<=739,"Good",IF(Linked[[#This Row],[Credit Score]]<=799,"Very Good",IF(Linked[[#This Row],[Credit Score]]>=800,"Excellent"))))) -> Poor | T75: 335724
A76: CUST0251 | B76: ACC00031 | C76: Danny Scott | D76: Female | E76: 29 | F76: Millennials | G76: North | H76: Teacher | I76: 45422 | J76: 2024 | K76: 822 days | L76: 124101 | M76: Medium | N76: Corporate | O76: Savings | P76: 44092 | Q76: 29493 | R76: 431 | S76: =IF(Linked[[#This Row],[Credit Score]]<=579,"Poor",IF(Linked[[#This Row],[Credit Score]]<=669,"Fair",IF(Linked[[#This Row],[Credit Score]]<=739,"Good",IF(Linked[[#This Row],[Credit Score]]<=799,"Very Good",IF(Linked[[#This Row],[Credit Score]]>=800,"Excellent"))))) -> Poor | T76: 0
A77: CUST0251 | B77: ACC00496 | C77: Danny Scott | D77: Female | E77: 29 | F77: Millennials | G77: North | H77: Teacher | I77: 45422 | J77: 2024 | K77: 822 days | L77: 124101 | M77: Medium | N77: Corporate | O77: Savings | P77: 43590 | Q77: 104927 | R77: 429 | S77: =IF(Linked[[#This Row],[Credit Score]]<=579,"Poor",IF(Linked[[#This Row],[Credit Score]]<=669,"Fair",IF(Linked[[#This Row],[Credit Score]]<=739,"Good",IF(Linked[[#This Row],[Credit Score]]<=799,"Very Good",IF(Linked[[#This Row],[Credit Score]]>=800,"Excellent"))))) -> Poor | T77: 0
... A83: CUST0303 | B83: ACC00032 | C83: Steven Black | D83: Male | E83: 52 | F83: Gen X | G83: West | H83: Doctor | I83: 44957 | J83: 2023 | K83: 1287 days | L83: 147118 | M83: High | N83: Corporate | O83: Checking | P83: 45191 | Q83: 485463 | R83: 371 | S83: =IF(Linked[[#This Row],[Credit Score]]<=579,"Poor",IF(Linked[[#This Row],[Credit Score]]<=669,"Fair",IF(Linked[[#This Row],[Credit Score]]<=739,"Good",IF(Linked[[#This Row],[Credit Score]]<=799,"Very Good",IF(Linked[[#This Row],[Credit Score]]>=800,"Excellent"))))) -> Poor | T83: 0
A84: CUST0303 | B84: ACC00471 | C84: Steven Black | D84: Male | E84: 52 | F84: Gen X | G84: West | H84: Doctor | I84: 44957 | J84: 2023 | K84: 1287 days | L84: 147118 | M84: High | N84: Corporate | O84: Savings | P84: 43318 | Q84: 243386 | R84: 634 | S84: =IF(Linked[[#This Row],[Credit Score]]<=579,"Poor",IF(Linked[[#This Row],[Credit Score]]<=669,"Fair",IF(Linked[[#This Row],[Credit Score]]<=739,"Good",IF(Linked[[#This Row],[Credit Score]]<=799,"Very Good",IF(Linked[[#This Row],[Credit Score]]>=800,"Excellent"))))) -> Fair | T84: 0 | U84: Default
A85: CUST0032 | B85: ACC00252 | C85: Steven Walker | D85: Male | E85: 56 | F85: Gen X | G85: North | H85: Retired | I85: 42565 | J85: 2016 | K85: 3679 days | L85: 93781 | M85: Medium | N85: Corporate | O85: CreditCard | P85: 42316 | Q85: 397650 | R85: 577 | S85: =IF(Linked[[#This Row],[Credit Score]]<=579,"Poor",IF(Linked[[#This Row],[Credit Score]]<=669,"Fair",IF(Linked[[#This Row],[Credit Score]]<=739,"Good",IF(Linked[[#This Row],[Credit Score]]<=799,"Very Good",IF(Linked[[#This Row],[Credit Score]]>=800,"Excellent"))))) -> Poor | T85: 0
A86: CUST0032 | B86: ACC00353 | C86: Steven Walker | D86: Male | E86: 56 | F86: Gen X | G86: North | H86: Retired | I86: 42565 | J86: 2016 | K86: 3679 days | L86: 93781 | M86: Medium | N86: Corporate | O86: CreditCard | P86: 42667 | Q86: 35931 | R86: 305 | S86: =IF(Linked[[#This Row],[Credit Score]]<=579,"Poor",IF(Linked[[#This Row],[Credit Score]]<=669,"Fair",IF(Linked[[#This Row],[Credit Score]]<=739,"Good",IF(Linked[[#This Row],[Credit Score]]<=799,"Very Good",IF(Linked[[#This Row],[Credit Score]]>=800,"Excellent"))))) -> Poor | T86: 0
A87: CUST0459 | B87: ACC00033 | C87: Raymond Holmes | D87: Male | E87: 18 | F87: Gen z | G87: South | H87: Teacher | I87: 43849 | J87: 2020 | K87: 2395 days | L87: 103310 | M87: Medium | N87: Corporate | O87: Checking | P87: 45495 | Q87: 466755 | R87: 486 | S87: =IF(Linked[[#This Row],[Credit Score]]<=579,"Poor",IF(Linked[[#This Row],[Credit Score]]<=669,"Fair",IF(Linked[[#This Row],[Credit Score]]<=739,"Good",IF(Linked[[#This Row],[Credit Score]]<=799,"Very Good",IF(Linked[[#This Row],[Credit Score]]>=800,"Excellent"))))) -> Poor | T87: 0 | U87: Default
A88: CUST0313 | B88: ACC00034 | C88: Amy Thornton | D88: Female | E88: 61 | F88: Boomers | G88: South | H88: Engineer | I88: 43566 | J88: 2019 | K88: 2678 days | L88: 150406 | M88: High | N88: Retail | O88: CreditCard | P88: 42433 | Q88: 293851 | R88: 785 | S88: =IF(Linked[[#This Row],[Credit Score]]<=579,"Poor",IF(Linked[[#This Row],[Credit Score]]<=669,"Fair",IF(Linked[[#This Row],[Credit Score]]<=739,"Good",IF(Linked[[#This Row],[Credit Score]]<=799,"Very Good",IF(Linked[[#This Row],[Credit Score]]>=800,"Excellent"))))) -> Very Good | T88: 0
A89: CUST0313 | B89: ACC00100 | C89: Amy Thornton | D89: Female | E89: 61 | F89: Boomers | G89: South | H89: Engineer | I89: 43566 | J89: 2019 | K89: 2678 days | L89: 150406 | M89: High | N89: Retail | O89: Checking | P89: 45303 | Q89: 346658 | R89: 716 | S89: =IF(Linked[[#This Row],[Credit Score]]<=579,"Poor",IF(Linked[[#This Row],[Credit Score]]<=669,"Fair",IF(Linked[[#This Row],[Credit Score]]<=739,"Good",IF(Linked[[#This Row],[Credit Score]]<=799,"Very Good",IF(Linked[[#This Row],[Credit Score]]>=800,"Excellent"))))) -> Good | T89: 0
A90: CUST0313 | B90: ACC00174 | C90: Amy Thornton | D90: Female | E90: 61 | F90: Boomers | G90: South | H90: Engineer | I90: 43566 | J90: 2019 | K90: 2678 days | L90: 150406 | M90: High | N90: Retail | O90: Checking | P90: 45000 | Q90: 347424 | R90: 674 | S90: =IF(Linked[[#This Row],[Credit Score]]<=579,"Poor",IF(Linked[[#This Row],[Credit Score]]<=669,"Fair",IF(Linked[[#This Row],[Credit Score]]<=739,"Good",IF(Linked[[#This Row],[Credit Score]]<=799,"Very Good",IF(Linked[[#This Row],[Credit Score]]>=800,"Excellent"))))) -> Good | T90: 0 | U90: Rejected
A91: CUST0313 | B91: ACC00477 | C91: Amy Thornton | D91: Female | E91: 61 | F91: Boomers | G91: South | H91: Engineer | I91: 43566 | J91: 2019 | K91: 2678 days | L91: 150406 | M91: High | N91: Retail | O91: Checking | P91: 43856 | Q91: 274535 | R91: 349 | S91: =IF(Linked[[#This Row],[Credit Score]]<=579,"Poor",IF(Linked[[#This Row],[Credit Score]]<=669,"Fair",IF(Linked[[#This Row],[Credit Score]]<=739,"Good",IF(Linked[[#This Row],[Credit Score]]<=799,"Very Good",IF(Linked[[#This Row],[Credit Score]]>=800,"Excellent"))))) -> Poor | T91: 246766 | U91: Rejected
A92: CUST0034 | B92: ACC00425 | C92: Brooke Carlson | D92: Female | E92: 59 | F92: Gen X | G92: West | H92: Student | I92: 44513 | J92: 2021 | K92: 1731 days | L92: 66600 | M92: Low | N92: Corporate | O92: Checking | P92: 45521 | Q92: 438164 | R92: 582 | S92: =IF(Linked[[#This Row],[Credit Score]]<=579,"Poor",IF(Linked[[#This Row],[Credit Score]]<=669,"Fair",IF(Linked[[#This Row],[Credit Score]]<=739,"Good",IF(Linked[[#This Row],[Credit Score]]<=799,"Very Good",IF(Linked[[#This Row],[Credit Score]]>=800,"Excellent"))))) -> Fair | T92: 0 | U92: Approved
A93: CUST0118 | B93: ACC00035 | C93: Shawn Randolph | D93: Female | E93: 42 | F93: Millennials | G93: South | H93: Banker | I93: 45720 | J93: 2025 | K93: 524 days | L93: 88344 | M93: Medium | N93: Retail | O93: Savings | P93: 43495 | Q93: 199886 | R93: 490 | S93: =IF(Linked[[#This Row],[Credit Score]]<=579,"Poor",IF(Linked[[#This Row],[Credit Score]]<=669,"Fair",IF(Linked[[#This Row],[Credit Score]]<=739,"Good",IF(Linked[[#This Row],[Credit Score]]<=799,"Very Good",IF(Linked[[#This Row],[Credit Score]]>=800,"Excellent"))))) -> Poor | T93: 0
A94: CUST0118 | B94: ACC00066 | C94: Shawn Randolph | D94: Female | E94: 42 | F94: Millennials | G94: South | H94: Banker | I94: 45720 | J94: 2025 | K94: 524 days | L94: 88344 | M94: Medium | N94: Retail | O94: Checking | P94: 45846 | Q94: 2187 | R94: 799 | S94: =IF(Linked[[#This Row],[Credit Score]]<=579,"Poor",IF(Linked[[#This Row],[Credit Score]]<=669,"Fair",IF(Linked[[#This Row],[Credit Score]]<=739,"Good",IF(Linked[[#This Row],[Credit Score]]<=799,"Very Good",IF(Linked[[#This Row],[Credit Score]]>=800,"Excellent"))))) -> Very Good | T94: 0
A95: CUST0035 | B95: ACC00075 | C95: Kevin Marshall | D95: Female | E95: 72 | F95: Boomers | G95: East | H95: Banker | I95: 42533 | J95: 2016 | K95: 3711 days | L95: 96898 | M95: Medium | N95: Corporate | O95: Checking | P95: 43741 | Q95: 419705 | R95: 614 | S95: =IF(Linked[[#This Row],[Credit Score]]<=579,"Poor",IF(Linked[[#This Row],[Credit Score]]<=669,"Fair",IF(Linked[[#This Row],[Credit Score]]<=739,"Good",IF(Linked[[#This Row],[Credit Score]]<=799,"Very Good",IF(Linked[[#This Row],[Credit Score]]>=800,"Excellent"))))) -> Fair | T95: 0
A96: CUST0301 | B96: ACC00036 | C96: Regina Schultz | D96: Male | E96: 48 | F96: Gen X | G96: South | H96: Doctor | I96: 45334 | J96: 2024 | K96: 910 days | L96: 70861 | M96: Low | N96: Retail | O96: CreditCard | P96: 44385 | Q96: 138368 | R96: 721 | S96: =IF(Linked[[#This Row],[Credit Score]]<=579,"Poor",IF(Linked[[#This Row],[Credit Score]]<=669,"Fair",IF(Linked[[#This Row],[Credit Score]]<=739,"Good",IF(Linked[[#This Row],[Credit Score]]<=799,"Very Good",IF(Linked[[#This Row],[Credit Score]]>=800,"Excellent"))))) -> Good | T96: 0
A97: CUST0301 | B97: ACC00140 | C97: Regina Schultz | D97: Male | E97: 48 | F97: Gen X | G97: South | H97: Doctor | I97: 45334 | J97: 2024 | K97: 910 days | L97: 70861 | M97: Low | N97: Retail | O97: Savings | P97: 44660 | Q97: 64925 | R97: 446 | S97: =IF(Linked[[#This Row],[Credit Score]]<=579,"Poor",IF(Linked[[#This Row],[Credit Score]]<=669,"Fair",IF(Linked[[#This Row],[Credit Score]]<=739,"Good",IF(Linked[[#This Row],[Credit Score]]<=799,"Very Good",IF(Linked[[#This Row],[Credit Score]]>=800,"Excellent"))))) -> Poor | T97: 0
A98: CUST0036 | B98: ACC00114 | C98: Bradley Moore | D98: Male | E98: 43 | F98: Millennials | G98: East | H98: Banker | I98: 42902 | J98: 2017 | K98: 3342 days | L98: 169369 | M98: High | N98: Retail | O98: Savings | P98: 44873 | Q98: 289662 | R98: 406 | S98: =IF(Linked[[#This Row],[Credit Score]]<=579,"Poor",IF(Linked[[#This Row],[Credit Score]]<=669,"Fair",IF(Linked[[#This Row],[Credit Score]]<=739,"Good",IF(Linked[[#This Row],[Credit Score]]<=799,"Very Good",IF(Linked[[#This Row],[Credit Score]]>=800,"Excellent"))))) -> Poor | T98: 0
A99: CUST0161 | B99: ACC00037 | C99: David Sanders | D99: Male | E99: 22 | F99: Gen z | G99: East | H99: Doctor | I99: 44252 | J99: 2021 | K99: 1992 days | L99: 93609 | M99: Medium | N99: Retail | O99: Savings | P99: 44430 | Q99: 156470 | R99: 419 | S99: =IF(Linked[[#This Row],[Credit Score]]<=579,"Poor",IF(Linked[[#This Row],[Credit Score]]<=669,"Fair",IF(Linked[[#This Row],[Credit Score]]<=739,"Good",IF(Linked[[#This Row],[Credit Score]]<=799,"Very Good",IF(Linked[[#This Row],[Credit Score]]>=800,"Excellent"))))) -> Poor | T99: 0
A100: CUST0161 | B100: ACC00194 | C100: David Sanders | D100: Male | E100: 22 | F100: Gen z | G100: East | H100: Doctor | I100: 44252 | J100: 2021 | K100: 1992 days | L100: 93609 | M100: Medium | N100: Retail | O100: CreditCard | P100: 44176 | Q100: 404015 | R100: 581 | S100: =IF(Linked[[#This Row],[Credit Score]]<=579,"Poor",IF(Linked[[#This Row],[Credit Score]]<=669,"Fair",IF(Linked[[#This Row],[Credit Score]]<=739,"Good",IF(Linked[[#This Row],[Credit Score]]<=799,"Very Good",IF(Linked[[#This Row],[Credit Score]]>=800,"Excellent"))))) -> Fair | T100: 0
A101: CUST0401 | B101: ACC00038 | C101: Kelsey Rodriguez | D101: Female | E101: 71 | F101: Boomers | G101: West | H101: Retired | I101: 44100 | J101: 2020 | K101: 2144 days | L101: 199436 | M101: High | N101: Private | O101: Savings | P101: 43619 | Q101: 297986 | R101: 519 | S101: =IF(Linked[[#This Row],[Credit Score]]<=579,"Poor",IF(Linked[[#This Row],[Credit Score]]<=669,"Fair",IF(Linked[[#This Row],[Credit Score]]<=739,"Good",IF(Linked[[#This Row],[Credit Score]]<=799,"Very Good",IF(Linked[[#This Row],[Credit Score]]>=800,"Excellent"))))) -> Poor | T101: 5654
A102: CUST0401 | B102: ACC00485 | C102: Kelsey Rodriguez | D102: Female | E102: 71 | F102: Boomers | G102: West | H102: Retired | I102: 44100 | J102: 2020 | K102: 2144 days | L102: 199436 | M102: High | N102: Private | O102: Savings | P102: 44719 | Q102: 181429 | R102: 458 | S102: =IF(Linked[[#This Row],[Credit Score]]<=579,"Poor",IF(Linked[[#This Row],[Credit Score]]<=669,"Fair",IF(Linked[[#This Row],[Credit Score]]<=739,"Good",IF(Linked[[#This Row],[Credit Score]]<=799,"Very Good",IF(Linked[[#This Row],[Credit Score]]>=800,"Excellent"))))) -> Poor | T102: 0
A103: CUST0198 | B103: ACC00039 | C103: Sarah Santiago | D103: Female | E103: 27 | F103: Gen z | G103: North | H103: Trader | I103: 43945 | J103: 2020 | K103: 2299 days | L103: 72307 | M103: Low | N103: Retail | O103: Savings | P103: 45596 | Q103: 13261 | R103: 352 | S103: =IF(Linked[[#This Row],[Credit Score]]<=579,"Poor",IF(Linked[[#This Row],[Credit Score]]<=669,"Fair",IF(Linked[[#This Row],[Credit Score]]<=739,"Good",IF(Linked[[#This Row],[Credit Score]]<=799,"Very Good",IF(Linked[[#This Row],[Credit Score]]>=800,"Excellent"))))) -> Poor | T103: 59633
A104: CUST0198 | B104: ACC00046 | C104: Sarah Santiago | D104: Female | E104: 27 | F104: Gen z | G104: North | H104: Trader | I104: 43945 | J104: 2020 | K104: 2299 days | L104: 72307 | M104: Low | N104: Retail | O104: CreditCard | P104: 45413 | Q104: 275796 | R104: 371 | S104: =IF(Linked[[#This Row],[Credit Score]]<=579,"Poor",IF(Linked[[#This Row],[Credit Score]]<=669,"Fair",IF(Linked[[#This Row],[Credit Score]]<=739,"Good",IF(Linked[[#This Row],[Credit Score]]<=799,"Very Good",IF(Linked[[#This Row],[Credit Score]]>=800,"Excellent"))))) -> Poor | T104: 0
A105: CUST0198 | B105: ACC00068 | C105: Sarah Santiago | D105: Female | E105: 27 | F105: Gen z | G105: North | H105: Trader | I105: 43945 | J105: 2020 | K105: 2299 days | L105: 72307 | M105: Low | N105: Retail | O105: Savings | P105: 42605 | Q105: 297242 | R105: 780 | S105: =IF(Linked[[#This Row],[Credit Score]]<=579,"Poor",IF(Linked[[#This Row],[Credit Score]]<=669,"Fair",IF(Linked[[#This Row],[Credit Score]]<=739,"Good",IF(Linked[[#This Row],[Credit Score]]<=799,"Very Good",IF(Linked[[#This Row],[Credit Score]]>=800,"Excellent"))))) -> Very Good | T105: 0 | U105: Default
...

Sheet Dashboard

Sheet Pivot Table
B2: Count of Account | C2: Average of Credit Score | D2: Average of Balance
B3: 800 | C3: 579.52625 | D3: 265426.42 | G3: Key Performance Indicators
H4: Total | K4: Average Balance by Customer Segment
A5: Count of Account type by users | G5: AVG loan Amount | K5: Row Labels | L5: Average of Balance
A6: Row Labels | B6: Count of CustomerID | G6: No of Accounts | H6: =GETPIVOTDATA("Count of Account",$B$2) -> 800 | K6: Private | L6: 275113.66
A7: Savings | B7: 303 | G7: AVG balance | H7: =GETPIVOTDATA("Average of Balance",$B$2) -> 265426.42 | K7: Retail | L7: 267102.03
A8: Checking | B8: 246 | G8: AVG Credit Score | H8: =GETPIVOTDATA("Average of Credit Score",$B$2) -> 579.52625 | K8: Corporate | L8: 259460.32
A9: CreditCard | B9: 169 | K9: Grand Total | L9: 265426.42
A10: Loan | B10: 82
A11: Grand Total | B11: 800
A12: Average Credit Score Of Each accoun type | D12: Average Blance of Each Account Type | G12: Count of Loan Status | J12: count of Accounts By Region
A13: Row Labels | B13: Average of Credit Score | C13: Credit score Bracket | D13: Row Labels | E13: Average of Balance | G13: Row Labels | H13: Average of Credit Score | J13: Row Labels | K13: Count of AccountID | M13: Row Labels | N13: Average of Balance
A14: Checking | B14: 578.67073 | C14: ='Customers Account'!Y12 -> 0 | D14: Checking | E14: 275053.37 | G14: Approved | H14: 580.50877 | J14: South | K14: 235 | M14: Boomers | N14: 264878.39
A15: CreditCard | B15: 574.92899 | C15: ='Customers Account'!Y15 -> 0 | D15: CreditCard | E15: 257636.54 | G15: Rejected | H15: 591.81159 | J15: East | K15: 204 | M15: Gen X | N15: 247707.3
A16: Loan | B16: 564 | C16: ='Customers Account'!Y14 -> 0 | D16: Loan | E16: 290089.96 | G16: Grand Total | H16: 586.69841 | J16: North | K16: 193 | M16: Gen z | N16: 267779.71
A17: Savings | B17: 586.9868 | C17: ='Customers Account'!Y13 -> 0 | D17: Savings | E17: 255280.7 | J17: West | K17: 168 | M17: Millennials | N17: 282099.39
A18: Grand Total | B18: 579.52625 | C18: ='Customers Account'!Y10 -> 0 | D18: Grand Total | E18: 265426.42 | J18: Grand Total | K18: 800 | M18: Grand Total | N18: 265426.42
A20: Count of account type by age bracket
A21: Count of AccountID | B21: Column Labels | H21: Average credit score of Loan Status | K21: Average Yealy Balance
A22: Row Labels | B22: Boomers | C22: Gen X | D22: Gen z | E22: Millennials | F22: Grand Total | H22: Row Labels | I22: Average of Credit Score | K22: Row Labels | L22: Average of Balance
A23: Checking | B23: 49 | C23: 73 | D23: 38 | E23: 86 | F23: 246 | H23: Approved | I23: 580.50877 | K23: 2015 | L23: 265345.57
A24: CreditCard | B24: 41 | C24: 56 | D24: 30 | E24: 42 | F24: 169 | H24: Default | I24: 574.95833 | K24: 2016 | L24: 303577.76
A25: Loan | B25: 15 | C25: 20 | D25: 16 | E25: 31 | F25: 82 | H25: Rejected | I25: 591.81159 | K25: 2017 | L25: 259810.36
A26: Savings | B26: 70 | C26: 90 | D26: 63 | E26: 80 | F26: 303 | H26: (blank) | I26: 578.43291 | K26: 2018 | L26: 240614.63
A27: Grand Total | B27: 175 | C27: 239 | D27: 147 | E27: 239 | F27: 800 | H27: Grand Total | I27: 579.52625 | K27: 2019 | L27: 254128.83
K28: 2020 | L28: 259193.11
K29: 2021 | L29: 285277.08
K30: 2022 | L30: 285062.26
K31: 2023 | L31: 262055.24
K32: 2024 | L32: 243471.72
K33: 2025 | L33: 281619.89
K34: Grand Total | L34: 265426.42

Sheet Accounts
A1: AccountID | B1: CustomerID | C1: Account_Type | D1: Open_Date | E1: Balance | F1: Credit_Score | G1: Loan_Amount | H1: Loan_Status
A2: ACC00001 | B2: CUST0305 | C2: Checking | D2: 43258 | E2: 363265 | F2: 698 | G2: 0
A3: ACC00002 | B3: CUST0319 | C3: Savings | D3: 45670 | E3: 282169 | F3: 405 | G3: 0
A4: ACC00003 | B4: CUST0366 | C4: Savings | D4: 43852 | E4: 397674 | F4: 570 | G4: 0
A5: ACC00004 | B5: CUST0211 | C5: Savings | D5: 44837 | E5: 63610 | F5: 802 | G5: 401875 | H5: Rejected
A6: ACC00005 | B6: CUST0406 | C6: Savings | D6: 44039 | E6: 70843 | F6: 824 | G6: 458505
A7: ACC00006 | B7: CUST0152 | C7: Checking | D7: 44185 | E7: 107237 | F7: 331 | G7: 163666
A8: ACC00007 | B8: CUST0109 | C8: CreditCard | D8: 44160 | E8: 477177 | F8: 692 | G8: 120819
A9: ACC00008 | B9: CUST0076 | C9: Checking | D9: 45487 | E9: 180903 | F9: 339 | G9: 0
A10: ACC00009 | B10: CUST0030 | C10: CreditCard | D10: 42340 | E10: 174499 | F10: 517 | G10: 0
A11: ACC00010 | B11: CUST0314 | C11: Loan | D11: 45493 | E11: 487025 | F11: 381 | G11: 0
A12: ACC00011 | B12: CUST0486 | C12: CreditCard | D12: 45351 | E12: 130299 | F12: 500 | G12: 0
A13: ACC00012 | B13: CUST0117 | C13: Checking | D13: 44010 | E13: 431722 | F13: 746 | G13: 278365
A14: ACC00013 | B14: CUST0415 | C14: Checking | D14: 45860 | E14: 5668 | F14: 727 | G14: 0 | H14: Approved
A15: ACC00014 | B15: CUST0356 | C15: Checking | D15: 44587 | E15: 222542 | F15: 337 | G15: 18569
A16: ACC00015 | B16: CUST0192 | C16: Savings | D16: 45438 | E16: 178267 | F16: 510 | G16: 0
A17: ACC00016 | B17: CUST0019 | C17: Savings | D17: 43064 | E17: 335377 | F17: 743 | G17: 0
A18: ACC00017 | B18: CUST0432 | C18: Loan | D18: 44333 | E18: 155489 | F18: 626 | G18: 207630
A19: ACC00018 | B19: CUST0173 | C19: CreditCard | D19: 44007 | E19: 344126 | F19: 526 | G19: 0
A20: ACC00019 | B20: CUST0228 | C20: Savings | D20: 44694 | E20: 106133 | F20: 347 | G20: 0 | H20: Rejected
A21: ACC00020 | B21: CUST0350 | C21: Checking | D21: 43335 | E21: 272895 | F21: 317 | G21: 0
A22: ACC00021 | B22: CUST0183 | C22: CreditCard | D22: 43980 | E22: 308362 | F22: 738 | G22: 0
A23: ACC00022 | B23: CUST0113 | C23: Savings | D23: 45635 | E23: 388793 | F23: 486 | G23: 258078
A24: ACC00023 | B24: CUST0183 | C24: Savings | D24: 45186 | E24: 269496 | F24: 644 | G24: 0 | H24: Default
A25: ACC00024 | B25: CUST0481 | C25: CreditCard | D25: 43146 | E25: 210124 | F25: 523 | G25: 0
A26: ACC00025 | B26: CUST0146 | C26: Checking | D26: 42535 | E26: 88835 | F26: 787 | G26: 485443
A27: ACC00026 | B27: CUST0319 | C27: Savings | D27: 43851 | E27: 97493 | F27: 528 | G27: 0
A28: ACC00027 | B28: CUST0116 | C28: Checking | D28: 45203 | E28: 291071 | F28: 689 | G28: 196007
A29: ACC00028 | B29: CUST0113 | C29: CreditCard | D29: 43189 | E29: 172166 | F29: 487 | G29: 0 | H29: Default
A30: ACC00029 | B30: CUST0251 | C30: Checking | D30: 43955 | E30: 101948 | F30: 569 | G30: 335724
A31: ACC00030 | B31: CUST0476 | C31: Savings | D31: 43461 | E31: 185194 | F31: 609 | G31: 0
A32: ACC00031 | B32: CUST0251 | C32: Savings | D32: 44092 | E32: 29493 | F32: 431 | G32: 0
A33: ACC00032 | B33: CUST0303 | C33: Checking | D33: 45191 | E33: 485463 | F33: 371 | G33: 0
A34: ACC00033 | B34: CUST0459 | C34: Checking | D34: 45495 | E34: 466755 | F34: 486 | G34: 0 | H34: Default
A35: ACC00034 | B35: CUST0313 | C35: CreditCard | D35: 42433 | E35: 293851 | F35: 785 | G35: 0
A36: ACC00035 | B36: CUST0118 | C36: Savings | D36: 43495 | E36: 199886 | F36: 490 | G36: 0
A37: ACC00036 | B37: CUST0301 | C37: CreditCard | D37: 44385 | E37: 138368 | F37: 721 | G37: 0
A38: ACC00037 | B38: CUST0161 | C38: Savings | D38: 44430 | E38: 156470 | F38: 419 | G38: 0
A39: ACC00038 | B39: CUST0401 | C39: Savings | D39: 43619 | E39: 297986 | F39: 519 | G39: 5654
A40: ACC00039 | B40: CUST0198 | C40: Savings | D40: 45596 | E40: 13261 | F40: 352 | G40: 59633
A41: ACC00040 | B41: CUST0260 | C41: Savings | D41: 44121 | E41: 76709 | F41: 750 | G41: 0 | H41: Rejected
A42: ACC00041 | B42: CUST0148 | C42: Checking | D42: 45740 | E42: 95985 | F42: 711 | G42: 0
A43: ACC00042 | B43: CUST0240 | C43: Checking | D43: 44171 | E43: 368760 | F43: 536 | G43: 0
A44: ACC00043 | B44: CUST0047 | C44: Savings | D44: 45200 | E44: 449920 | F44: 705 | G44: 0
A45: ACC00044 | B45: CUST0475 | C45: Checking | D45: 42460 | E45: 329317 | F45: 721 | G45: 0
A46: ACC00045 | B46: CUST0399 | C46: Savings | D46: 45290 | E46: 293925 | F46: 546 | G46: 0
A47: ACC00046 | B47: CUST0198 | C47: CreditCard | D47: 45413 | E47: 275796 | F47: 371 | G47: 0
A48: ACC00047 | B48: CUST0047 | C48: Loan | D48: 44782 | E48: 267247 | F48: 484 | G48: 0
A49: ACC00048 | B49: CUST0078 | C49: Savings | D49: 45583 | E49: 287644 | F49: 305 | G49: 485398
A50: ACC00049 | B50: CUST0124 | C50: Checking | D50: 43835 | E50: 246404 | F50: 505 | G50: 0
A51: ACC00050 | B51: CUST0075 | C51: Savings | D51: 45414 | E51: 100336 | F51: 843 | G51: 316011 | H51: Rejected
A52: ACC00051 | B52: CUST0359 | C52: Savings | D52: 43810 | E52: 428745 | F52: 686 | G52: 449244
A53: ACC00052 | B53: CUST0137 | C53: Savings | D53: 42425 | E53: 113499 | F53: 375 | G53: 0 | H53: Rejected
A54: ACC00053 | B54: CUST0090 | C54: CreditCard | D54: 43028 | E54: 149524 | F54: 476 | G54: 0
A55: ACC00054 | B55: CUST0400 | C55: Checking | D55: 42626 | E55: 311537 | F55: 648 | G55: 0
A56: ACC00055 | B56: CUST0325 | C56: Savings | D56: 45145 | E56: 424390 | F56: 554 | G56: 0
A57: ACC00056 | B57: CUST0500 | C57: CreditCard | D57: 44318 | E57: 457666 | F57: 607 | G57: 0
A58: ACC00057 | B58: CUST0061 | C58: Checking | D58: 45750 | E58: 166508 | F58: 644 | G58: 222508
A59: ACC00058 | B59: CUST0138 | C59: CreditCard | D59: 43942 | E59: 309550 | F59: 426 | G59: 0 | H59: Rejected
A60: ACC00059 | B60: CUST0050 | C60: Checking | D60: 43744 | E60: 325203 | F60: 586 | G60: 0
A61: ACC00060 | B61: CUST0259 | C61: Checking | D61: 44768 | E61: 147026 | F61: 786 | G61: 0
A62: ACC00061 | B62: CUST0461 | C62: Savings | D62: 43375 | E62: 344866 | F62: 682 | G62: 0
A63: ACC00062 | B63: CUST0107 | C63: Savings | D63: 44407 | E63: 250819 | F63: 705 | G63: 0
A64: ACC00063 | B64: CUST0113 | C64: Loan | D64: 43721 | E64: 12356 | F64: 687 | G64: 0
A65: ACC00064 | B65: CUST0350 | C65: Savings | D65: 43714 | E65: 128128 | F65: 824 | G65: 0
A66: ACC00065 | B66: CUST0254 | C66: Loan | D66: 42707 | E66: 491715 | F66: 575 | G66: 0
A67: ACC00066 | B67: CUST0118 | C67: Checking | D67: 45846 | E67: 2187 | F67: 799 | G67: 0
A68: ACC00067 | B68: CUST0493 | C68: Savings | D68: 42482 | E68: 339387 | F68: 636 | G68: 0 | H68: Rejected
A69: ACC00068 | B69: CUST0198 | C69: Savings | D69: 42605 | E69: 297242 | F69: 780 | G69: 0 | H69: Default
A70: ACC00069 | B70: CUST0337 | C70: Savings | D70: 43964 | E70: 485687 | F70: 572 | G70: 0
A71: ACC00070 | B71: CUST0365 | C71: Loan | D71: 44843 | E71: 152297 | F71: 357 | G71: 0
A72: ACC00071 | B72: CUST0051 | C72: Checking | D72: 42702 | E72: 134678 | F72: 627 | G72: 0
A73: ACC00072 | B73: CUST0245 | C73: Savings | D73: 44558 | E73: 319764 | F73: 408 | G73: 0 | H73: Approved
A74: ACC00073 | B74: CUST0403 | C74: Savings | D74: 43267 | E74: 426044 | F74: 578 | G74: 373894
A75: ACC00074 | B75: CUST0426 | C75: Savings | D75: 45406 | E75: 126270 | F75: 627 | G75: 394187
A76: ACC00075 | B76: CUST0035 | C76: Checking | D76: 43741 | E76: 419705 | F76: 614 | G76: 0
A77: ACC00076 | B77: CUST0302 | C77: Savings | D77: 43170 | E77: 276531 | F77: 773 | G77: 0
A78: ACC00077 | B78: CUST0410 | C78: CreditCard | D78: 45642 | E78: 331607 | F78: 410 | G78: 429606 | H78: Approved
A79: ACC00078 | B79: CUST0499 | C79: Savings | D79: 43803 | E79: 465048 | F79: 528 | G79: 0
A80: ACC00079 | B80: CUST0069 | C80: Savings | D80: 45733 | E80: 489196 | F80: 796 | G80: 149233
A81: ACC00080 | B81: CUST0349 | C81: Checking | D81: 42365 | E81: 242998 | F81: 455 | G81: 0 | H81: Rejected
A82: ACC00081 | B82: CUST0320 | C82: Checking | D82: 43834 | E82: 395807 | F82: 772 | G82: 0 | H82: Approved
A83: ACC00082 | B83: CUST0421 | C83: Loan | D83: 42626 | E83: 241503 | F83: 571 | G83: 111379 | H83: Approved
A84: ACC00083 | B84: CUST0468 | C84: Checking | D84: 43147 | E84: 441732 | F84: 301 | G84: 231905 | H84: Approved
A85: ACC00084 | B85: CUST0049 | C85: Savings | D85: 43176 | E85: 353827 | F85: 810 | G85: 0
A86: ACC00085 | B86: CUST0405 | C86: Checking | D86: 43642 | E86: 62061 | F86: 585 | G86: 0
A87: ACC00086 | B87: CUST0074 | C87: Savings | D87: 44444 | E87: 235497 | F87: 312 | G87: 0 | H87: Default
A88: ACC00087 | B88: CUST0192 | C88: Savings | D88: 43238 | E88: 459952 | F88: 797 | G88: 0 | H88: Approved
A89: ACC00088 | B89: CUST0261 | C89: Loan | D89: 42693 | E89: 81257 | F89: 537 | G89: 0
A90: ACC00089 | B90: CUST0356 | C90: CreditCard | D90: 43262 | E90: 61753 | F90: 393 | G90: 146835
A91: ACC00090 | B91: CUST0070 | C91: Loan | D91: 44429 | E91: 346918 | F91: 637 | G91: 0
A92: ACC00091 | B92: CUST0090 | C92: Checking | D92: 44681 | E92: 404303 | F92: 470 | G92: 98109
A93: ACC00092 | B93: CUST0260 | C93: Checking | D93: 43749 | E93: 424032 | F93: 766 | G93: 0
A94: ACC00093 | B94: CUST0126 | C94: Savings | D94: 45069 | E94: 23408 | F94: 442 | G94: 0
A95: ACC00094 | B95: CUST0231 | C95: Savings | D95: 45287 | E95: 124116 | F95: 500 | G95: 0 | H95: Rejected
A96: ACC00095 | B96: CUST0295 | C96: CreditCard | D96: 43128 | E96: 498492 | F96: 479 | G96: 426175
A97: ACC00096 | B97: CUST0498 | C97: Savings | D97: 45492 | E97: 131208 | F97: 663 | G97: 0
A98: ACC00097 | B98: CUST0419 | C98: CreditCard | D98: 44472 | E98: 17413 | F98: 778 | G98: 128076
A99: ACC00098 | B99: CUST0129 | C99: CreditCard | D99: 42587 | E99: 113650 | F99: 770 | G99: 163177
A100: ACC00099 | B100: CUST0280 | C100: Savings | D100: 43608 | E100: 59500 | F100: 683 | G100: 0
...

Sheet MetroBankAccounts
A1: AccountID | B1: CustomerID | C1: Account_Type | D1: Open_Date | E1: Balance | F1: Credit_Score | G1: Loan_Amount | H1: Loan_Status
A2: ACC00001 | B2: CUST0305 | C2: Checking | D2: 43258 | E2: 363265 | F2: 698 | G2: 0
A3: ACC00002 | B3: CUST0319 | C3: Savings | D3: 45670 | E3: 282169 | F3: 405 | G3: 0
A4: ACC00003 | B4: CUST0366 | C4: Savings | D4: 43852 | E4: 397674 | F4: 570 | G4: 0
A5: ACC00004 | B5: CUST0211 | C5: Savings | D5: 44837 | E5: 63610 | F5: 802 | G5: 401875 | H5: Rejected
A6: ACC00005 | B6: CUST0406 | C6: Savings | D6: 44039 | E6: 70843 | F6: 824 | G6: 458505
A7: ACC00006 | B7: CUST0152 | C7: Checking | D7: 44185 | E7: 107237 | F7: 331 | G7: 163666
A8: ACC00007 | B8: CUST0109 | C8: CreditCard | D8: 44160 | E8: 477177 | F8: 692 | G8: 120819
A9: ACC00008 | B9: CUST0076 | C9: Checking | D9: 45487 | E9: 180903 | F9: 339 | G9: 0
A10: ACC00009 | B10: CUST0030 | C10: CreditCard | D10: 42340 | E10: 174499 | F10: 517 | G10: 0
A11: ACC00010 | B11: CUST0314 | C11: Loan | D11: 45493 | E11: 487025 | F11: 381 | G11: 0
A12: ACC00011 | B12: CUST0486 | C12: CreditCard | D12: 45351 | E12: 130299 | F12: 500 | G12: 0
A13: ACC00012 | B13: CUST0117 | C13: Checking | D13: 44010 | E13: 431722 | F13: 746 | G13: 278365
A14: ACC00013 | B14: CUST0415 | C14: Checking | D14: 45860 | E14: 5668 | F14: 727 | G14: 0 | H14: Approved
A15: ACC00014 | B15: CUST0356 | C15: Checking | D15: 44587 | E15: 222542 | F15: 337 | G15: 18569
A16: ACC00015 | B16: CUST0192 | C16: Savings | D16: 45438 | E16: 178267 | F16: 510 | G16: 0
A17: ACC00016 | B17: CUST0019 | C17: Savings | D17: 43064 | E17: 335377 | F17: 743 | G17: 0
A18: ACC00017 | B18: CUST0432 | C18: Loan | D18: 44333 | E18: 155489 | F18: 626 | G18: 207630
A19: ACC00018 | B19: CUST0173 | C19: CreditCard | D19: 44007 | E19: 344126 | F19: 526 | G19: 0
A20: ACC00019 | B20: CUST0228 | C20: Savings | D20: 44694 | E20: 106133 | F20: 347 | G20: 0 | H20: Rejected
A21: ACC00020 | B21: CUST0350 | C21: Checking | D21: 43335 | E21: 272895 | F21: 317 | G21: 0
A22: ACC00021 | B22: CUST0183 | C22: CreditCard | D22: 43980 | E22: 308362 | F22: 738 | G22: 0
A23: ACC00022 | B23: CUST0113 | C23: Savings | D23: 45635 | E23: 388793 | F23: 486 | G23: 258078
A24: ACC00023 | B24: CUST0183 | C24: Savings | D24: 45186 | E24: 269496 | F24: 644 | G24: 0 | H24: Default
A25: ACC00024 | B25: CUST0481 | C25: CreditCard | D25: 43146 | E25: 210124 | F25: 523 | G25: 0
A26: ACC00025 | B26: CUST0146 | C26: Checking | D26: 42535 | E26: 88835 | F26: 787 | G26: 485443
A27: ACC00026 | B27: CUST0319 | C27: Savings | D27: 43851 | E27: 97493 | F27: 528 | G27: 0
A28: ACC00027 | B28: CUST0116 | C28: Checking | D28: 45203 | E28: 291071 | F28: 689 | G28: 196007
A29: ACC00028 | B29: CUST0113 | C29: CreditCard | D29: 43189 | E29: 172166 | F29: 487 | G29: 0 | H29: Default
A30: ACC00029 | B30: CUST0251 | C30: Checking | D30: 43955 | E30: 101948 | F30: 569 | G30: 335724
A31: ACC00030 | B31: CUST0476 | C31: Savings | D31: 43461 | E31: 185194 | F31: 609 | G31: 0
A32: ACC00031 | B32: CUST0251 | C32: Savings | D32: 44092 | E32: 29493 | F32: 431 | G32: 0
A33: ACC00032 | B33: CUST0303 | C33: Checking | D33: 45191 | E33: 485463 | F33: 371 | G33: 0
A34: ACC00033 | B34: CUST0459 | C34: Checking | D34: 45495 | E34: 466755 | F34: 486 | G34: 0 | H34: Default
A35: ACC00034 | B35: CUST0313 | C35: CreditCard | D35: 42433 | E35: 293851 | F35: 785 | G35: 0
A36: ACC00035 | B36: CUST0118 | C36: Savings | D36: 43495 | E36: 199886 | F36: 490 | G36: 0
A37: ACC00036 | B37: CUST0301 | C37: CreditCard | D37: 44385 | E37: 138368 | F37: 721 | G37: 0
A38: ACC00037 | B38: CUST0161 | C38: Savings | D38: 44430 | E38: 156470 | F38: 419 | G38: 0
A39: ACC00038 | B39: CUST0401 | C39: Savings | D39: 43619 | E39: 297986 | F39: 519 | G39: 5654
A40: ACC00039 | B40: CUST0198 | C40: Savings | D40: 45596 | E40: 13261 | F40: 352 | G40: 59633
A41: ACC00040 | B41: CUST0260 | C41: Savings | D41: 44121 | E41: 76709 | F41: 750 | G41: 0 | H41: Rejected
A42: ACC00041 | B42: CUST0148 | C42: Checking | D42: 45740 | E42: 95985 | F42: 711 | G42: 0
A43: ACC00042 | B43: CUST0240 | C43: Checking | D43: 44171 | E43: 368760 | F43: 536 | G43: 0
A44: ACC00043 | B44: CUST0047 | C44: Savings | D44: 45200 | E44: 449920 | F44: 705 | G44: 0
A45: ACC00044 | B45: CUST0475 | C45: Checking | D45: 42460 | E45: 329317 | F45: 721 | G45: 0
A46: ACC00045 | B46: CUST0399 | C46: Savings | D46: 45290 | E46: 293925 | F46: 546 | G46: 0
A47: ACC00046 | B47: CUST0198 | C47: CreditCard | D47: 45413 | E47: 275796 | F47: 371 | G47: 0
A48: ACC00047 | B48: CUST0047 | C48: Loan | D48: 44782 | E48: 267247 | F48: 484 | G48: 0
A49: ACC00048 | B49: CUST0078 | C49: Savings | D49: 45583 | E49: 287644 | F49: 305 | G49: 485398
A50: ACC00049 | B50: CUST0124 | C50: Checking | D50: 43835 | E50: 246404 | F50: 505 | G50: 0
A51: ACC00050 | B51: CUST0075 | C51: Savings | D51: 45414 | E51: 100336 | F51: 843 | G51: 316011 | H51: Rejected
A52: ACC00051 | B52: CUST0359 | C52: Savings | D52: 43810 | E52: 428745 | F52: 686 | G52: 449244
A53: ACC00052 | B53: CUST0137 | C53: Savings | D53: 42425 | E53: 113499 | F53: 375 | G53: 0 | H53: Rejected
A54: ACC00053 | B54: CUST0090 | C54: CreditCard | D54: 43028 | E54: 149524 | F54: 476 | G54: 0
A55: ACC00054 | B55: CUST0400 | C55: Checking | D55: 42626 | E55: 311537 | F55: 648 | G55: 0
A56: ACC00055 | B56: CUST0325 | C56: Savings | D56: 45145 | E56: 424390 | F56: 554 | G56: 0
A57: ACC00056 | B57: CUST0500 | C57: CreditCard | D57: 44318 | E57: 457666 | F57: 607 | G57: 0
A58: ACC00057 | B58: CUST0061 | C58: Checking | D58: 45750 | E58: 166508 | F58: 644 | G58: 222508
A59: ACC00058 | B59: CUST0138 | C59: CreditCard | D59: 43942 | E59: 309550 | F59: 426 | G59: 0 | H59: Rejected
A60: ACC00059 | B60: CUST0050 | C60: Checking | D60: 43744 | E60: 325203 | F60: 586 | G60: 0
A61: ACC00060 | B61: CUST0259 | C61: Checking | D61: 44768 | E61: 147026 | F61: 786 | G61: 0
A62: ACC00061 | B62: CUST0461 | C62: Savings | D62: 43375 | E62: 344866 | F62: 682 | G62: 0
A63: ACC00062 | B63: CUST0107 | C63: Savings | D63: 44407 | E63: 250819 | F63: 705 | G63: 0
A64: ACC00063 | B64: CUST0113 | C64: Loan | D64: 43721 | E64: 12356 | F64: 687 | G64: 0
A65: ACC00064 | B65: CUST0350 | C65: Savings | D65: 43714 | E65: 128128 | F65: 824 | G65: 0
A66: ACC00065 | B66: CUST0254 | C66: Loan | D66: 42707 | E66: 491715 | F66: 575 | G66: 0
A67: ACC00066 | B67: CUST0118 | C67: Checking | D67: 45846 | E67: 2187 | F67: 799 | G67: 0
A68: ACC00067 | B68: CUST0493 | C68: Savings | D68: 42482 | E68: 339387 | F68: 636 | G68: 0 | H68: Rejected
A69: ACC00068 | B69: CUST0198 | C69: Savings | D69: 42605 | E69: 297242 | F69: 780 | G69: 0 | H69: Default
A70: ACC00069 | B70: CUST0337 | C70: Savings | D70: 43964 | E70: 485687 | F70: 572 | G70: 0
A71: ACC00070 | B71: CUST0365 | C71: Loan | D71: 44843 | E71: 152297 | F71: 357 | G71: 0
A72: ACC00071 | B72: CUST0051 | C72: Checking | D72: 42702 | E72: 134678 | F72: 627 | G72: 0
A73: ACC00072 | B73: CUST0245 | C73: Savings | D73: 44558 | E73: 319764 | F73: 408 | G73: 0 | H73: Approved
A74: ACC00073 | B74: CUST0403 | C74: Savings | D74: 43267 | E74: 426044 | F74: 578 | G74: 373894
A75: ACC00074 | B75: CUST0426 | C75: Savings | D75: 45406 | E75: 126270 | F75: 627 | G75: 394187
A76: ACC00075 | B76: CUST0035 | C76: Checking | D76: 43741 | E76: 419705 | F76: 614 | G76: 0
A77: ACC00076 | B77: CUST0302 | C77: Savings | D77: 43170 | E77: 276531 | F77: 773 | G77: 0
A78: ACC00077 | B78: CUST0410 | C78: CreditCard | D78: 45642 | E78: 331607 | F78: 410 | G78: 429606 | H78: Approved
A79: ACC00078 | B79: CUST0499 | C79: Savings | D79: 43803 | E79: 465048 | F79: 528 | G79: 0
A80: ACC00079 | B80: CUST0069 | C80: Savings | D80: 45733 | E80: 489196 | F80: 796 | G80: 149233
A81: ACC00080 | B81: CUST0349 | C81: Checking | D81: 42365 | E81: 242998 | F81: 455 | G81: 0 | H81: Rejected
A82: ACC00081 | B82: CUST0320 | C82: Checking | D82: 43834 | E82: 395807 | F82: 772 | G82: 0 | H82: Approved
A83: ACC00082 | B83: CUST0421 | C83: Loan | D83: 42626 | E83: 241503 | F83: 571 | G83: 111379 | H83: Approved
A84: ACC00083 | B84: CUST0468 | C84: Checking | D84: 43147 | E84: 441732 | F84: 301 | G84: 231905 | H84: Approved
A85: ACC00084 | B85: CUST0049 | C85: Savings | D85: 43176 | E85: 353827 | F85: 810 | G85: 0
A86: ACC00085 | B86: CUST0405 | C86: Checking | D86: 43642 | E86: 62061 | F86: 585 | G86: 0
A87: ACC00086 | B87: CUST0074 | C87: Savings | D87: 44444 | E87: 235497 | F87: 312 | G87: 0 | H87: Default
A88: ACC00087 | B88: CUST0192 | C88: Savings | D88: 43238 | E88: 459952 | F88: 797 | G88: 0 | H88: Approved
A89: ACC00088 | B89: CUST0261 | C89: Loan | D89: 42693 | E89: 81257 | F89: 537 | G89: 0
A90: ACC00089 | B90: CUST0356 | C90: CreditCard | D90: 43262 | E90: 61753 | F90: 393 | G90: 146835
A91: ACC00090 | B91: CUST0070 | C91: Loan | D91: 44429 | E91: 346918 | F91: 637 | G91: 0
A92: ACC00091 | B92: CUST0090 | C92: Checking | D92: 44681 | E92: 404303 | F92: 470 | G92: 98109
A93: ACC00092 | B93: CUST0260 | C93: Checking | D93: 43749 | E93: 424032 | F93: 766 | G93: 0
A94: ACC00093 | B94: CUST0126 | C94: Savings | D94: 45069 | E94: 23408 | F94: 442 | G94: 0
A95: ACC00094 | B95: CUST0231 | C95: Savings | D95: 45287 | E95: 124116 | F95: 500 | G95: 0 | H95: Rejected
A96: ACC00095 | B96: CUST0295 | C96: CreditCard | D96: 43128 | E96: 498492 | F96: 479 | G96: 426175
A97: ACC00096 | B97: CUST0498 | C97: Savings | D97: 45492 | E97: 131208 | F97: 663 | G97: 0
A98: ACC00097 | B98: CUST0419 | C98: CreditCard | D98: 44472 | E98: 17413 | F98: 778 | G98: 128076
A99: ACC00098 | B99: CUST0129 | C99: CreditCard | D99: 42587 | E99: 113650 | F99: 770 | G99: 163177
A100: ACC00099 | B100: CUST0280 | C100: Savings | D100: 43608 | E100: 59500 | F100: 683 | G100: 0
...
